{"data":[{"table":"ActiveUser","data":[{"UserId":"yeasin.ali@brac.net","UserName":"Md. Yeasin Ali","UserPin":"116813","Token":"61905740ba2b7","EventId":"1654","DateStart":"2021-11-14 12:00:00","DateEnd":"2021-11-18 12:00:00","EventRole":"1","BranchCode":"0423","BranchName":"Krishnapur","AreaName":"Manikgonj Sadar","RegionName":"Manikgonj","DivisionName":"Central-1","LastDownload":"2021-11-18 10:38:29","ProjectCode":"0"}]},{"table":"Respondents","data":[{"Id":"130757","EventId":"1654","SectionId":"2","SubSectionId":"0","OrgNo":"2225","OrgMemNo":"","MemberName":"BARAHIRCHAR( OTUP-1)","AdmissionDate":"2021-11-15 00:00:00","LoanNo":"43","DisbDate":"2021-11-15 00:00:00","Amount":"16","CONo":"00142343","COName":"JADAB CHANDRA DAS","MonitorNo":"2","Status":"S","Updated_At":"2021-11-14 13:02:29.903798"},{"Id":"130761","EventId":"1654","SectionId":"2","SubSectionId":"0","OrgNo":"2218","OrgMemNo":"","MemberName":"BARTTA","AdmissionDate":"2021-11-16 00:00:00","LoanNo":"19","DisbDate":"2021-11-16 00:00:00","Amount":"9","CONo":"00115621","COName":"MD. SERAJUL ISLAM","MonitorNo":"2","Status":"S","Updated_At":"2021-11-14 13:03:00.93243"},{"Id":"130763","EventId":"1654","SectionId":"2","SubSectionId":"0","OrgNo":"2002","OrgMemNo":"","MemberName":"BARABARAHI","AdmissionDate":"2021-11-17 00:00:00","LoanNo":"29","DisbDate":"2021-11-17 00:00:00","Amount":"26","CONo":"00196518","COName":"MANISH KANTI MISTRY","MonitorNo":"2","Status":"S","Updated_At":"2021-11-14 13:03:16.889361"},{"Id":"130764","EventId":"1654","SectionId":"2","SubSectionId":"","OrgNo":"2048","OrgMemNo":"","MemberName":"DIHI KATIGRAM","AdmissionDate":"2021-11-15 00:00:00","LoanNo":"27","DisbDate":"2021-11-15 00:00:00","Amount":"12","CONo":"00142441","COName":"MD. FARID ULLAH","MonitorNo":"1","Status":"S","Updated_At":"2021-11-14 19:03:29"},{"Id":"130765","EventId":"1654","SectionId":"2","SubSectionId":"","OrgNo":"2239","OrgMemNo":"","MemberName":"RAJIBPUR( ELA)","AdmissionDate":"2021-11-17 00:00:00","LoanNo":"23","DisbDate":"2021-11-17 00:00:00","Amount":"18","CONo":"00253899","COName":"LIPI AKTER","MonitorNo":"1","Status":"S","Updated_At":"2021-11-14 19:03:51"},{"Id":"131025","EventId":"1654","SectionId":"4","SubSectionId":"2","OrgNo":"2048","OrgMemNo":"","MemberName":"DIHI KATIGRAM","AdmissionDate":"2021-11-15 00:00:00","LoanNo":"0","DisbDate":"2021-11-15 00:00:00","Amount":"0","CONo":"00142441","COName":"MD. FARID ULLAH","MonitorNo":"1","Status":"S","Updated_At":"2021-11-15 11:23:38"},{"Id":"131014","EventId":"1654","SectionId":"4","SubSectionId":"4","OrgNo":"2048","OrgMemNo":"","MemberName":"DIHI KATIGRAM","AdmissionDate":"2021-11-15 00:00:00","LoanNo":"0","DisbDate":"2021-11-15 00:00:00","Amount":"0","CONo":"00142441","COName":"MD. FARID ULLAH","MonitorNo":"1","Status":"S","Updated_At":"2021-11-15 13:17:39"},{"Id":"131091","EventId":"1654","SectionId":"4","SubSectionId":"2","OrgNo":"2225","OrgMemNo":"","MemberName":"BARAHIRCHAR( OTUP-1)","AdmissionDate":"2021-11-15 00:00:00","LoanNo":"0","DisbDate":"2021-11-15 00:00:00","Amount":"0","CONo":"00142343","COName":"JADAB CHANDRA DAS","MonitorNo":"2","Status":"S","Updated_At":"2021-11-15 08:45:04.431043"},{"Id":"131093","EventId":"1654","SectionId":"4","SubSectionId":"4","OrgNo":"2225","OrgMemNo":"","MemberName":"BARAHIRCHAR( OTUP-1)","AdmissionDate":"2021-11-15 00:00:00","LoanNo":"0","DisbDate":"2021-11-15 00:00:00","Amount":"0","CONo":"00142343","COName":"JADAB CHANDRA DAS","MonitorNo":"2","Status":"S","Updated_At":"2021-11-15 08:46:20.714343"},{"Id":"131137","EventId":"1654","SectionId":"4","SubSectionId":"6","OrgNo":"2304","OrgMemNo":"000029","MemberName":"Rohima","AdmissionDate":"2011-05-04 00:00:00","LoanNo":"14897811","DisbDate":"2017-08-13 00:00:00","Amount":"80000","CONo":"00196518","COName":"MANISH KANTI MISTRY","MonitorNo":"1","Status":"S","Updated_At":"2021-11-15 16:22:33"},{"Id":"131147","EventId":"1654","SectionId":"4","SubSectionId":"6","OrgNo":"2271","OrgMemNo":"000134","MemberName":"Kakali","AdmissionDate":"2010-02-22 00:00:00","LoanNo":"14897171","DisbDate":"2018-03-15 00:00:00","Amount":"200000","CONo":"00142343","COName":"JADAB CHANDRA DAS","MonitorNo":"1","Status":"S","Updated_At":"2021-11-15 16:51:04"},{"Id":"131148","EventId":"1654","SectionId":"4","SubSectionId":"6","OrgNo":"5010","OrgMemNo":"000072","MemberName":"Hena","AdmissionDate":"2007-04-22 00:00:00","LoanNo":"14899913","DisbDate":"2017-11-12 00:00:00","Amount":"200000","CONo":"00115621","COName":"MD. SERAJUL ISLAM","MonitorNo":"1","Status":"S","Updated_At":"2021-11-15 16:51:04"},{"Id":"131152","EventId":"1654","SectionId":"4","SubSectionId":"6","OrgNo":"2191","OrgMemNo":"000541","MemberName":"Moyna\/Azmot","AdmissionDate":"2017-05-18 00:00:00","LoanNo":"14895840","DisbDate":"2018-02-22 00:00:00","Amount":"100000","CONo":"00115621","COName":"MD. SERAJUL ISLAM","MonitorNo":"1","Status":"S","Updated_At":"2021-11-15 17:01:35"},{"Id":"131153","EventId":"1654","SectionId":"4","SubSectionId":"6","OrgNo":"5004","OrgMemNo":"000194","MemberName":"Lovely \/Jahangir","AdmissionDate":"2016-09-29 00:00:00","LoanNo":"14899414","DisbDate":"2018-04-11 00:00:00","Amount":"100000","CONo":"00142441","COName":"MD. FARID ULLAH","MonitorNo":"1","Status":"S","Updated_At":"2021-11-15 17:03:08"},{"Id":"131185","EventId":"1654","SectionId":"4","SubSectionId":"8","OrgNo":"2071","OrgMemNo":"000523","MemberName":"Lakhi\/Amzad","AdmissionDate":"2014-11-05 00:00:00","LoanNo":"14895003","DisbDate":"2019-06-19 00:00:00","Amount":"300000","CONo":"00142343","COName":"JADAB CHANDRA DAS","MonitorNo":"2","Status":"S","Updated_At":"2021-11-15 12:33:25.151067"},{"Id":"131184","EventId":"1654","SectionId":"4","SubSectionId":"8","OrgNo":"2232","OrgMemNo":"000225","MemberName":"Salma\/Yousub","AdmissionDate":"2013-08-27 00:00:00","LoanNo":"14896601","DisbDate":"2019-03-20 00:00:00","Amount":"80000","CONo":"00142441","COName":"MD. FARID ULLAH","MonitorNo":"2","Status":"S","Updated_At":"2021-11-15 12:30:17.265889"},{"Id":"131186","EventId":"1654","SectionId":"4","SubSectionId":"8","OrgNo":"2355","OrgMemNo":"000001","MemberName":"Sarmin Aketer-Sohel Rana","AdmissionDate":"2019-01-15 00:00:00","LoanNo":"14898678","DisbDate":"2019-09-16 00:00:00","Amount":"80000","CONo":"00142343","COName":"JADAB CHANDRA DAS","MonitorNo":"2","Status":"S","Updated_At":"2021-11-15 12:35:23.102962"},{"Id":"131262","EventId":"1654","SectionId":"4","SubSectionId":"8","OrgNo":"2282","OrgMemNo":"000212","MemberName":"Razia\/Rezaul","AdmissionDate":"2016-07-19 00:00:00","LoanNo":"14897640","DisbDate":"2019-04-09 00:00:00","Amount":"40000","CONo":"00099037","COName":"KANON BALA SARKAR","MonitorNo":"2","Status":"S","Updated_At":"2021-11-15 14:58:52.406608"},{"Id":"131263","EventId":"1654","SectionId":"5","SubSectionId":"5","OrgNo":"2232","OrgMemNo":"000235","MemberName":"Taslima\/Ab Alim","AdmissionDate":"2013-11-07 00:00:00","LoanNo":"14896606","DisbDate":"2019-09-22 00:00:00","Amount":"200000","CONo":"00142441","COName":"MD. FARID ULLAH","MonitorNo":"2","Status":"S","Updated_At":"2021-11-15 15:02:41.334506"},{"Id":"131360","EventId":"1654","SectionId":"2","SubSectionId":"","OrgNo":"5006","OrgMemNo":"","MemberName":"DAYARAM PUR","AdmissionDate":"2021-11-16 00:00:00","LoanNo":"23","DisbDate":"2021-11-16 00:00:00","Amount":"7","CONo":"00142441","COName":"MD. FARID ULLAH","MonitorNo":"1","Status":"S","Updated_At":"2021-11-16 08:50:08"},{"Id":"131404","EventId":"1654","SectionId":"2","SubSectionId":"","OrgNo":"5006","OrgMemNo":"000036","MemberName":"Rusia\/Ab Jalil","AdmissionDate":"2013-12-15 00:00:00","LoanNo":"24918832","DisbDate":"2021-08-23 00:00:00","Amount":"50000","CONo":"00142441","COName":"MD. FARID ULLAH","MonitorNo":"1","Status":"S","Updated_At":"2021-11-16 10:01:34"},{"Id":"131419","EventId":"1654","SectionId":"4","SubSectionId":"2","OrgNo":"5006","OrgMemNo":"","MemberName":"DAYARAM PUR","AdmissionDate":"2021-11-16 00:00:00","LoanNo":"0","DisbDate":"2021-11-16 00:00:00","Amount":"0","CONo":"00142441","COName":"MD. FARID ULLAH","MonitorNo":"1","Status":"S","Updated_At":"2021-11-16 10:21:06"},{"Id":"131506","EventId":"1654","SectionId":"3","SubSectionId":"3","OrgNo":"2015","OrgMemNo":"000404","MemberName":"Sufia\/Khalil","AdmissionDate":"2017-12-10 00:00:00","LoanNo":"22876999","DisbDate":"2021-02-18 00:00:00","Amount":"30000","CONo":"00253899","COName":"LIPI AKTER","MonitorNo":"1","Status":"S","Updated_At":"2021-11-16 13:07:34"},{"Id":"131507","EventId":"1654","SectionId":"3","SubSectionId":"3","OrgNo":"2337","OrgMemNo":"000183","MemberName":"MONORA","AdmissionDate":"2021-02-15 00:00:00","LoanNo":"0","DisbDate":"1900-02-01 00:00:00","Amount":"0","CONo":"00142441","COName":"MD. FARID ULLAH","MonitorNo":"1","Status":"S","Updated_At":"2021-11-16 13:09:52"},{"Id":"131511","EventId":"1654","SectionId":"3","SubSectionId":"3","OrgNo":"2358","OrgMemNo":"000025","MemberName":"Nazma Begum","AdmissionDate":"2019-05-13 00:00:00","LoanNo":"0","DisbDate":"1900-02-01 00:00:00","Amount":"0","CONo":"00142441","COName":"MD. FARID ULLAH","MonitorNo":"1","Status":"S","Updated_At":"2021-11-16 13:12:33"},{"Id":"131512","EventId":"1654","SectionId":"3","SubSectionId":"3","OrgNo":"2268","OrgMemNo":"000275","MemberName":"BILKIS BEGUM","AdmissionDate":"2020-10-13 00:00:00","LoanNo":"0","DisbDate":"1900-02-01 00:00:00","Amount":"0","CONo":"00253899","COName":"LIPI AKTER","MonitorNo":"1","Status":"S","Updated_At":"2021-11-16 13:14:08"},{"Id":"131515","EventId":"1654","SectionId":"3","SubSectionId":"3","OrgNo":"2331","OrgMemNo":"000071","MemberName":"Alekzan ","AdmissionDate":"2020-02-03 00:00:00","LoanNo":"0","DisbDate":"1900-02-01 00:00:00","Amount":"0","CONo":"00253899","COName":"LIPI AKTER","MonitorNo":"1","Status":"S","Updated_At":"2021-11-16 13:16:17"},{"Id":"131536","EventId":"1654","SectionId":"4","SubSectionId":"2","OrgNo":"2218","OrgMemNo":"","MemberName":"BARTTA","AdmissionDate":"2021-11-16 00:00:00","LoanNo":"0","DisbDate":"2021-11-16 00:00:00","Amount":"0","CONo":"00115621","COName":"MD. SERAJUL ISLAM","MonitorNo":"2","Status":"S","Updated_At":"2021-11-16 07:37:42.112636"},{"Id":"131544","EventId":"1654","SectionId":"2","SubSectionId":"0","OrgNo":"2218","OrgMemNo":"000440","MemberName":"RENA","AdmissionDate":"2020-11-17 00:00:00","LoanNo":"25536694","DisbDate":"2021-09-23 00:00:00","Amount":"75000","CONo":"00115621","COName":"MD. SERAJUL ISLAM","MonitorNo":"2","Status":"S","Updated_At":"2021-11-16 07:44:28.440919"},{"Id":"131545","EventId":"1654","SectionId":"2","SubSectionId":"0","OrgNo":"2218","OrgMemNo":"000441","MemberName":"BAYLA BEGUM","AdmissionDate":"2020-12-19 00:00:00","LoanNo":"26060896","DisbDate":"2021-10-21 00:00:00","Amount":"50000","CONo":"00115621","COName":"MD. SERAJUL ISLAM","MonitorNo":"2","Status":"S","Updated_At":"2021-11-16 07:44:45.00335"},{"Id":"131568","EventId":"1654","SectionId":"4","SubSectionId":"11","OrgNo":"2282","OrgMemNo":"000096","MemberName":"Zahanara Begum","AdmissionDate":"2010-05-11 00:00:00","LoanNo":"21766426","DisbDate":"2020-12-22 00:00:00","Amount":"99476","CONo":"00099037","COName":"KANON BALA SARKAR","MonitorNo":"1","Status":"S","Updated_At":"2021-11-16 15:01:41"},{"Id":"131582","EventId":"1654","SectionId":"4","SubSectionId":"11","OrgNo":"2197","OrgMemNo":"000338","MemberName":"Nazma Khatun-Abul","AdmissionDate":"2018-11-13 00:00:00","LoanNo":"21921768","DisbDate":"2020-12-27 00:00:00","Amount":"99722","CONo":"00115621","COName":"MD. SERAJUL ISLAM","MonitorNo":"1","Status":"S","Updated_At":"2021-11-16 15:46:27"},{"Id":"131585","EventId":"1654","SectionId":"4","SubSectionId":"11","OrgNo":"2337","OrgMemNo":"000183","MemberName":"MONORA","AdmissionDate":"2021-02-15 00:00:00","LoanNo":"22879636","DisbDate":"2021-02-18 00:00:00","Amount":"50000","CONo":"00142441","COName":"MD. FARID ULLAH","MonitorNo":"1","Status":"S","Updated_At":"2021-11-16 15:50:24"},{"Id":"131604","EventId":"1654","SectionId":"4","SubSectionId":"11","OrgNo":"2071","OrgMemNo":"000698","MemberName":"Julekha","AdmissionDate":"2019-04-30 00:00:00","LoanNo":"23091224","DisbDate":"2021-03-04 00:00:00","Amount":"30000","CONo":"00142343","COName":"JADAB CHANDRA DAS","MonitorNo":"1","Status":"S","Updated_At":"2021-11-16 16:39:30"},{"Id":"131606","EventId":"1654","SectionId":"4","SubSectionId":"11","OrgNo":"2303","OrgMemNo":"000089","MemberName":"MST MORJINA","AdmissionDate":"2020-11-16 00:00:00","LoanNo":"21497462","DisbDate":"2020-12-14 00:00:00","Amount":"20000","CONo":"00253899","COName":"LIPI AKTER","MonitorNo":"1","Status":"S","Updated_At":"2021-11-16 16:55:11"},{"Id":"131825","EventId":"1654","SectionId":"4","SubSectionId":"7","OrgNo":"2239","OrgMemNo":"000039","MemberName":"Mst.Rupali Akter","AdmissionDate":"2013-01-10 00:00:00","LoanNo":"20473469","DisbDate":"2020-10-29 00:00:00","Amount":"119723","CONo":"00253899","COName":"LIPI AKTER","MonitorNo":"1","Status":"S","Updated_At":"2021-11-17 09:26:26"},{"Id":"131826","EventId":"1654","SectionId":"4","SubSectionId":"7","OrgNo":"2239","OrgMemNo":"000405","MemberName":"Rita","AdmissionDate":"2020-01-23 00:00:00","LoanNo":"23398822","DisbDate":"2021-03-21 00:00:00","Amount":"30000","CONo":"00253899","COName":"LIPI AKTER","MonitorNo":"1","Status":"S","Updated_At":"2021-11-17 09:27:12"},{"Id":"131874","EventId":"1654","SectionId":"2","SubSectionId":"","OrgNo":"2239","OrgMemNo":"000390","MemberName":"SAHIDA BEGUM","AdmissionDate":"2018-01-30 00:00:00","LoanNo":"24844731","DisbDate":"2021-08-19 00:00:00","Amount":"50000","CONo":"00253899","COName":"LIPI AKTER","MonitorNo":"1","Status":"S","Updated_At":"2021-11-17 09:53:59"},{"Id":"131884","EventId":"1654","SectionId":"2","SubSectionId":"","OrgNo":"2239","OrgMemNo":"000069","MemberName":"AMENA BEGUM","AdmissionDate":"2014-02-26 00:00:00","LoanNo":"26152476","DisbDate":"2021-10-25 00:00:00","Amount":"220000","CONo":"00253899","COName":"LIPI AKTER","MonitorNo":"1","Status":"S","Updated_At":"2021-11-17 10:01:11"},{"Id":"131892","EventId":"1654","SectionId":"4","SubSectionId":"9","OrgNo":"2239","OrgMemNo":"000390","MemberName":"SAHIDA BEGUM","AdmissionDate":"2018-01-30 00:00:00","LoanNo":"24844731","DisbDate":"2021-08-19 00:00:00","Amount":"50000","CONo":"00253899","COName":"LIPI AKTER","MonitorNo":"1","Status":"S","Updated_At":"2021-11-17 10:09:07"},{"Id":"131915","EventId":"1654","SectionId":"4","SubSectionId":"2","OrgNo":"2239","OrgMemNo":"","MemberName":"RAJIBPUR( ELA)","AdmissionDate":"2021-11-17 00:00:00","LoanNo":"0","DisbDate":"2021-11-17 00:00:00","Amount":"0","CONo":"00253899","COName":"LIPI AKTER","MonitorNo":"1","Status":"S","Updated_At":"2021-11-17 10:24:34"},{"Id":"131925","EventId":"1654","SectionId":"4","SubSectionId":"9","OrgNo":"2239","OrgMemNo":"002248","MemberName":"Shaheda","AdmissionDate":"2020-11-26 00:00:00","LoanNo":"25611372","DisbDate":"2021-09-28 00:00:00","Amount":"50000","CONo":"00253899","COName":"LIPI AKTER","MonitorNo":"1","Status":"S","Updated_At":"2021-11-17 10:41:41"},{"Id":"131973","EventId":"1654","SectionId":"4","SubSectionId":"10","OrgNo":"2234","OrgMemNo":"000084","MemberName":"RUBIA BEGUM","AdmissionDate":"2014-09-16 00:00:00","LoanNo":"26226690","DisbDate":"2021-10-28 00:00:00","Amount":"49676","CONo":"00196518","COName":"MANISH KANTI MISTRY","MonitorNo":"1","Status":"S","Updated_At":"2021-11-17 11:32:34"},{"Id":"131989","EventId":"1654","SectionId":"4","SubSectionId":"10","OrgNo":"2338","OrgMemNo":"000041","MemberName":"Hasina Begum","AdmissionDate":"2015-04-02 00:00:00","LoanNo":"26140625","DisbDate":"2021-10-25 00:00:00","Amount":"100000","CONo":"00142343","COName":"JADAB CHANDRA DAS","MonitorNo":"1","Status":"S","Updated_At":"2021-11-17 11:57:45"},{"Id":"132031","EventId":"1654","SectionId":"4","SubSectionId":"2","OrgNo":"2002","OrgMemNo":"","MemberName":"BARABARAHI","AdmissionDate":"2021-11-17 00:00:00","LoanNo":"0","DisbDate":"2021-11-17 00:00:00","Amount":"0","CONo":"00196518","COName":"MANISH KANTI MISTRY","MonitorNo":"2","Status":"S","Updated_At":"2021-11-17 09:20:54.182192"},{"Id":"132032","EventId":"1654","SectionId":"2","SubSectionId":"0","OrgNo":"2002","OrgMemNo":"000538","MemberName":"Razia\/Sakat","AdmissionDate":"2014-05-15 00:00:00","LoanNo":"25381708","DisbDate":"2021-09-19 00:00:00","Amount":"80000","CONo":"00196518","COName":"MANISH KANTI MISTRY","MonitorNo":"2","Status":"S","Updated_At":"2021-11-17 09:23:34.33236"},{"Id":"132041","EventId":"1654","SectionId":"4","SubSectionId":"10","OrgNo":"2014","OrgMemNo":"000410","MemberName":"Falani-Tota Miah","AdmissionDate":"2018-11-14 00:00:00","LoanNo":"26232997","DisbDate":"2021-10-31 00:00:00","Amount":"39485","CONo":"00099037","COName":"KANON BALA SARKAR","MonitorNo":"1","Status":"S","Updated_At":"2021-11-17 15:43:10"},{"Id":"132052","EventId":"1654","SectionId":"4","SubSectionId":"10","OrgNo":"2318","OrgMemNo":"000085","MemberName":"SALIMA","AdmissionDate":"2020-09-12 00:00:00","LoanNo":"26147106","DisbDate":"2021-10-25 00:00:00","Amount":"50000","CONo":"00142441","COName":"MD. FARID ULLAH","MonitorNo":"1","Status":"S","Updated_At":"2021-11-17 16:26:37"},{"Id":"132057","EventId":"1654","SectionId":"4","SubSectionId":"10","OrgNo":"2175","OrgMemNo":"003096","MemberName":"FIROZA BEGUM","AdmissionDate":"2021-10-27 00:00:00","LoanNo":"26227515","DisbDate":"2021-10-28 00:00:00","Amount":"40000","CONo":"00253899","COName":"LIPI AKTER","MonitorNo":"1","Status":"S","Updated_At":"2021-11-17 17:02:03"},{"Id":"132093","EventId":"1654","SectionId":"4","SubSectionId":"7","OrgNo":"2002","OrgMemNo":"000386","MemberName":"Moyna","AdmissionDate":"2010-06-02 00:00:00","LoanNo":"22416573","DisbDate":"2021-01-24 00:00:00","Amount":"60000","CONo":"00196518","COName":"MANISH KANTI MISTRY","MonitorNo":"2","Status":"S","Updated_At":"2021-11-17 12:40:14.1718"},{"Id":"132094","EventId":"1654","SectionId":"4","SubSectionId":"7","OrgNo":"2002","OrgMemNo":"000574","MemberName":"Jahida Begum-Korim","AdmissionDate":"2019-04-17 00:00:00","LoanNo":"14893861","DisbDate":"2020-01-09 00:00:00","Amount":"80000","CONo":"00196518","COName":"MANISH KANTI MISTRY","MonitorNo":"2","Status":"S","Updated_At":"2021-11-17 12:41:23.91464"},{"Id":"132101","EventId":"1654","SectionId":"1","SubSectionId":"0","OrgNo":"2357","OrgMemNo":"000051","MemberName":"LIPI AKTER","AdmissionDate":"2021-11-01 00:00:00","LoanNo":"26414533","DisbDate":"2021-11-09 00:00:00","Amount":"60000","CONo":"00115621","COName":"MD. SERAJUL ISLAM","MonitorNo":"2","Status":"S","Updated_At":"2021-11-17 13:07:39.081831"},{"Id":"132100","EventId":"1654","SectionId":"1","SubSectionId":"0","OrgNo":"2357","OrgMemNo":"000052","MemberName":"HERA BEGUM","AdmissionDate":"2021-11-09 00:00:00","LoanNo":"26496904","DisbDate":"2021-11-11 00:00:00","Amount":"50000","CONo":"00115621","COName":"MD. SERAJUL ISLAM","MonitorNo":"2","Status":"S","Updated_At":"2021-11-17 13:05:26.128317"},{"Id":"132099","EventId":"1654","SectionId":"1","SubSectionId":"0","OrgNo":"5012","OrgMemNo":"000046","MemberName":"SUMI AKTER","AdmissionDate":"2021-11-10 00:00:00","LoanNo":"26489481","DisbDate":"2021-11-11 00:00:00","Amount":"25000","CONo":"00099037","COName":"KANON BALA SARKAR","MonitorNo":"2","Status":"S","Updated_At":"2021-11-17 13:03:18.623749"},{"Id":"132095","EventId":"1654","SectionId":"4","SubSectionId":"7","OrgNo":"2002","OrgMemNo":"000310","MemberName":"Sahedav","AdmissionDate":"2003-03-10 00:00:00","LoanNo":"21000146","DisbDate":"2020-11-21 00:00:00","Amount":"59987","CONo":"00196518","COName":"MANISH KANTI MISTRY","MonitorNo":"2","Status":"S","Updated_At":"2021-11-17 12:51:38.739788"},{"Id":"132096","EventId":"1654","SectionId":"4","SubSectionId":"9","OrgNo":"2002","OrgMemNo":"000573","MemberName":"Anjo Begum","AdmissionDate":"2019-03-20 00:00:00","LoanNo":"26146292","DisbDate":"2021-10-25 00:00:00","Amount":"80000","CONo":"00196518","COName":"MANISH KANTI MISTRY","MonitorNo":"2","Status":"S","Updated_At":"2021-11-17 12:54:32.985437"},{"Id":"132097","EventId":"1654","SectionId":"4","SubSectionId":"9","OrgNo":"2002","OrgMemNo":"000582","MemberName":"Suma","AdmissionDate":"2019-10-16 00:00:00","LoanNo":"26377546","DisbDate":"2021-11-08 00:00:00","Amount":"14837","CONo":"00196518","COName":"MANISH KANTI MISTRY","MonitorNo":"2","Status":"S","Updated_At":"2021-11-17 12:56:20.247289"},{"Id":"132098","EventId":"1654","SectionId":"4","SubSectionId":"9","OrgNo":"2002","OrgMemNo":"005564","MemberName":"PARVIN AKTER","AdmissionDate":"2020-12-21 00:00:00","LoanNo":"26471266","DisbDate":"2021-11-11 00:00:00","Amount":"20000","CONo":"00196518","COName":"MANISH KANTI MISTRY","MonitorNo":"2","Status":"S","Updated_At":"2021-11-17 12:57:48.390467"},{"Id":"132121","EventId":"1654","SectionId":"1","SubSectionId":"0","OrgNo":"2234","OrgMemNo":"000146","MemberName":"SONJITA KIRTONIYA","AdmissionDate":"2021-11-10 00:00:00","LoanNo":"26498226","DisbDate":"2021-11-11 00:00:00","Amount":"50000","CONo":"00196518","COName":"MANISH KANTI MISTRY","MonitorNo":"2","Status":"S","Updated_At":"2021-11-17 13:33:23.367911"},{"Id":"132122","EventId":"1654","SectionId":"1","SubSectionId":"0","OrgNo":"2273","OrgMemNo":"000414","MemberName":"SHAMPA AKTER","AdmissionDate":"2021-11-01 00:00:00","LoanNo":"26330602","DisbDate":"2021-11-07 00:00:00","Amount":"30000","CONo":"00142343","COName":"JADAB CHANDRA DAS","MonitorNo":"2","Status":"S","Updated_At":"2021-11-17 13:37:06.243258"},{"Id":"132129","EventId":"1654","SectionId":"4","SubSectionId":"8","OrgNo":"2280","OrgMemNo":"000261","MemberName":"Sultana","AdmissionDate":"2019-10-09 00:00:00","LoanNo":"14897563","DisbDate":"2019-10-13 00:00:00","Amount":"30000","CONo":"00196518","COName":"MANISH KANTI MISTRY","MonitorNo":"2","Status":"S","Updated_At":"2021-11-17 13:45:00.408034"},{"Id":"132142","EventId":"1654","SectionId":"5","SubSectionId":"5","OrgNo":"2016","OrgMemNo":"000415","MemberName":"Morium Begum-Nasir","AdmissionDate":"2019-01-10 00:00:00","LoanNo":"14894121","DisbDate":"2019-11-17 00:00:00","Amount":"50000","CONo":"00196518","COName":"MANISH KANTI MISTRY","MonitorNo":"2","Status":"S","Updated_At":"2021-11-17 13:53:39.177006"},{"Id":"132133","EventId":"1654","SectionId":"5","SubSectionId":"5","OrgNo":"2233","OrgMemNo":"000094","MemberName":"Laily\/Lal Miah","AdmissionDate":"2017-11-19 00:00:00","LoanNo":"14896752","DisbDate":"2019-03-13 00:00:00","Amount":"40000","CONo":"00253899","COName":"LIPI AKTER","MonitorNo":"2","Status":"S","Updated_At":"2021-11-17 13:50:46.618111"},{"Id":"132132","EventId":"1654","SectionId":"5","SubSectionId":"5","OrgNo":"2282","OrgMemNo":"000211","MemberName":"Sapna\/Jane Alom","AdmissionDate":"2016-05-18 00:00:00","LoanNo":"14897638","DisbDate":"2019-10-27 00:00:00","Amount":"20000","CONo":"00099037","COName":"KANON BALA SARKAR","MonitorNo":"2","Status":"S","Updated_At":"2021-11-17 13:50:07.14303"},{"Id":"132136","EventId":"1654","SectionId":"5","SubSectionId":"5","OrgNo":"2303","OrgMemNo":"000080","MemberName":"Lipi-Ajijul","AdmissionDate":"2019-02-18 00:00:00","LoanNo":"14897793","DisbDate":"2019-02-20 00:00:00","Amount":"50000","CONo":"00253899","COName":"LIPI AKTER","MonitorNo":"2","Status":"S","Updated_At":"2021-11-17 13:52:24.269024"},{"Id":"132187","EventId":"1654","SectionId":"5","SubSectionId":"3","OrgNo":"2304","OrgMemNo":"000119","MemberName":"Salina Akter","AdmissionDate":"2019-04-30 00:00:00","LoanNo":"22557157","DisbDate":"2021-02-04 00:00:00","Amount":"10000","CONo":"00196518","COName":"MANISH KANTI MISTRY","MonitorNo":"1","Status":"S","Updated_At":"2021-11-18 09:24:22"},{"Id":"132189","EventId":"1654","SectionId":"5","SubSectionId":"3","OrgNo":"2271","OrgMemNo":"000126","MemberName":"Vanu","AdmissionDate":"1999-08-09 00:00:00","LoanNo":"24588228","DisbDate":"2021-08-05 00:00:00","Amount":"50000","CONo":"00142343","COName":"JADAB CHANDRA DAS","MonitorNo":"1","Status":"S","Updated_At":"2021-11-18 09:33:21"},{"Id":"132213","EventId":"1654","SectionId":"5","SubSectionId":"3","OrgNo":"2318","OrgMemNo":"000004","MemberName":"Habia Khatun","AdmissionDate":"2012-03-15 00:00:00","LoanNo":"23656688","DisbDate":"2021-04-07 00:00:00","Amount":"25000","CONo":"00142441","COName":"MD. FARID ULLAH","MonitorNo":"1","Status":"S","Updated_At":"2021-11-18 10:38:44"},{"Id":"132214","EventId":"1654","SectionId":"5","SubSectionId":"3","OrgNo":"2282","OrgMemNo":"000341","MemberName":"Taslima Akter","AdmissionDate":"2020-03-22 00:00:00","LoanNo":"23498389","DisbDate":"2021-03-23 00:00:00","Amount":"50000","CONo":"00099037","COName":"KANON BALA SARKAR","MonitorNo":"1","Status":"S","Updated_At":"2021-11-18 10:39:07"},{"Id":"132219","EventId":"1654","SectionId":"5","SubSectionId":"3","OrgNo":"2195","OrgMemNo":"000557","MemberName":"Fatema Begum","AdmissionDate":"2020-03-09 00:00:00","LoanNo":"21935960","DisbDate":"2020-12-28 00:00:00","Amount":"50000","CONo":"00115621","COName":"MD. SERAJUL ISLAM","MonitorNo":"1","Status":"S","Updated_At":"2021-11-18 10:41:07"},{"Id":"132231","EventId":"1654","SectionId":"5","SubSectionId":"3","OrgNo":"2015","OrgMemNo":"000392","MemberName":"Julakha\/Sanowar","AdmissionDate":"2016-07-20 00:00:00","LoanNo":"22103714","DisbDate":"2021-01-11 00:00:00","Amount":"110000","CONo":"00253899","COName":"LIPI AKTER","MonitorNo":"1","Status":"S","Updated_At":"2021-11-18 10:51:24"}]},{"table":"SurveyData","data":[{"Id":"482922","EventId":"1654","SectionId":"4","SubSectionId":"2","OrgNo":"2048","OrgMemNo":"","Question":"1","Answer":"1","Score":"0","Remarks":"","MonitorNo":"1","Status":"S","Updated_At":"2021-11-18 16:32:01","Longi":"0","Lati":"0","Verified":"1"},{"Id":"482923","EventId":"1654","SectionId":"4","SubSectionId":"2","OrgNo":"2048","OrgMemNo":"","Question":"2","Answer":"1","Score":"0","Remarks":"","MonitorNo":"1","Status":"S","Updated_At":"2021-11-18 16:32:01","Longi":"0","Lati":"0","Verified":"1"},{"Id":"482924","EventId":"1654","SectionId":"4","SubSectionId":"2","OrgNo":"2048","OrgMemNo":"","Question":"3","Answer":"1","Score":"0","Remarks":"","MonitorNo":"1","Status":"S","Updated_At":"2021-11-18 16:32:01","Longi":"0","Lati":"0","Verified":"1"},{"Id":"482925","EventId":"1654","SectionId":"4","SubSectionId":"2","OrgNo":"2048","OrgMemNo":"","Question":"4","Answer":"0","Score":"1","Remarks":"","MonitorNo":"1","Status":"S","Updated_At":"2021-11-18 16:32:01","Longi":"0","Lati":"0","Verified":"1"},{"Id":"482926","EventId":"1654","SectionId":"4","SubSectionId":"2","OrgNo":"2048","OrgMemNo":"","Question":"5","Answer":"1","Score":"0","Remarks":"","MonitorNo":"1","Status":"S","Updated_At":"2021-11-18 16:32:01","Longi":"0","Lati":"0","Verified":"1"},{"Id":"482927","EventId":"1654","SectionId":"4","SubSectionId":"2","OrgNo":"2048","OrgMemNo":"","Question":"6","Answer":"1","Score":"0","Remarks":"","MonitorNo":"1","Status":"S","Updated_At":"2021-11-18 16:32:01","Longi":"0","Lati":"0","Verified":"1"},{"Id":"482928","EventId":"1654","SectionId":"4","SubSectionId":"3","OrgNo":"2048","OrgMemNo":"","Question":"1","Answer":"0","Score":"1","Remarks":"","MonitorNo":"1","Status":"S","Updated_At":"2021-11-18 16:32:01","Longi":"0","Lati":"0","Verified":"1"},{"Id":"482929","EventId":"1654","SectionId":"4","SubSectionId":"3","OrgNo":"2048","OrgMemNo":"","Question":"2","Answer":"0","Score":"1","Remarks":"","MonitorNo":"1","Status":"S","Updated_At":"2021-11-18 16:32:01","Longi":"0","Lati":"0","Verified":"1"},{"Id":"482930","EventId":"1654","SectionId":"4","SubSectionId":"3","OrgNo":"2048","OrgMemNo":"","Question":"3","Answer":"1","Score":"0","Remarks":"","MonitorNo":"1","Status":"S","Updated_At":"2021-11-18 16:32:01","Longi":"0","Lati":"0","Verified":"1"},{"Id":"482931","EventId":"1654","SectionId":"4","SubSectionId":"3","OrgNo":"2048","OrgMemNo":"","Question":"4","Answer":"1","Score":"0","Remarks":"","MonitorNo":"1","Status":"S","Updated_At":"2021-11-18 16:32:01","Longi":"0","Lati":"0","Verified":"1"},{"Id":"482935","EventId":"1654","SectionId":"4","SubSectionId":"4","OrgNo":"2048","OrgMemNo":"","Question":"1","Answer":"27","Score":"27","Remarks":"","MonitorNo":"1","Status":"S","Updated_At":"2021-11-18 16:32:01","Longi":"0","Lati":"0","Verified":"1"},{"Id":"482936","EventId":"1654","SectionId":"4","SubSectionId":"4","OrgNo":"2048","OrgMemNo":"","Question":"2","Answer":"24","Score":"24","Remarks":"\u09b6\u09be\u09b9\u09be\u09a8\u09be\u099c  \u09eb\u09e8\u09e7.\u09ae\u09be\u099c\u09c7\u09a6\u09be\u09eb\u09ea\u09eb.\u09ae\u09be\u09b2\u09be\u09eb\u09eb\u09ef ,\u09e9 \u099f\u09bf \u09aa\u09be\u09b6\u09ac\u0987 \u09aa\u09be\u0993\u09af\u09bc\u09be \u09af\u09be\u09af\u09bc\u09a8\u09bf \u09b8\u09a6\u09b8\u09cd\u09af \u09ac\u09be\u09a1\u09bc\u09bf\u09a4\u09c7 \u099b\u09bf\u09b2 \u09a8\u09be\n","MonitorNo":"1","Status":"S","Updated_At":"2021-11-18 16:32:01","Longi":"0","Lati":"0","Verified":"1"},{"Id":"482937","EventId":"1654","SectionId":"4","SubSectionId":"5","OrgNo":"2048","OrgMemNo":"","Question":"1","Answer":"28","Score":"28","Remarks":"\u09b8\u09be\u099c\u09c7\u09a6\u09be, \u09ea\u09e6\u09eb \u09b8\u09a6\u09b8\u09cd\u09af\u09b0 \u09aa\u09be\u09b6\u09ac\u0987 \u098f\u09a8\u09cd\u099f\u09bf \u09a8\u09be \u09a6\u09bf\u09af\u09bc\u09c7 \u0995\u09ae\u09cd\u09aa\u09bf\u0989\u099f\u09be\u09b0 \u09b8\u09c0\u099f\u09c7 \u09b8\u099c\u09cd\u099e\u09af\u09bc \u09e7\u09e6\u09e6\u09e6\u09e6 \u099f\u09be\u0995\u09be \u09ac\u09c7\u09b6\u09c0 \u099c\u09ae\u09be \u09aa\u09be\u0993\u09df\u09be \u09af\u09be\u09df \u0964 \u09a8\u09cb \u09b8\u09be\u0995\u09cd\u09b7\u09b0 \u09aa\u09be\u09b6\u09ac\u0987 \u09e9\u09eb\u09ed,\u09e9\u09ed\u09e8,\u09e9\u09ee\u09e6,\u09ea\u09e6\u09e8,\u09ea\u09e7\u09eb,\u09eb\u09e8\u09ee,\u09eb\u09e9\u09ec,\u09eb\u09e9\u09ef,\u09eb\u09eb\u09e7,\u09eb\u09ec\u09e6,\u09eb\u09ec\u09e8,\u09eb\u09ec\u09ec,\u09eb\u09ec\u09ed,\u09eb\u09ec\u09ef,\u09eb\u09ed\u09e7l\u09a8\u09cb \u09ac\u09c7\u09b8\u09bf\u0995 \u0987\u09a8\u09ab\u09b0\u09ae\u09c7\u09b6\u09a8 \u09eb\u09ec\u09e6,\u09ea\u09e6\u09eb\u09f7","MonitorNo":"1","Status":"S","Updated_At":"2021-11-18 16:32:01","Longi":"0","Lati":"0","Verified":"1"},{"Id":"482938","EventId":"1654","SectionId":"4","SubSectionId":"5","OrgNo":"2048","OrgMemNo":"","Question":"2","Answer":"27","Score":"27","Remarks":"","MonitorNo":"1","Status":"S","Updated_At":"2021-11-18 16:32:01","Longi":"0","Lati":"0","Verified":"1"},{"Id":"482939","EventId":"1654","SectionId":"4","SubSectionId":"5","OrgNo":"2048","OrgMemNo":"","Question":"3","Answer":"24","Score":"24","Remarks":"","MonitorNo":"1","Status":"S","Updated_At":"2021-11-18 16:32:01","Longi":"0","Lati":"0","Verified":"1"},{"Id":"482940","EventId":"1654","SectionId":"4","SubSectionId":"5","OrgNo":"2048","OrgMemNo":"","Question":"4","Answer":"26","Score":"26","Remarks":"","MonitorNo":"1","Status":"S","Updated_At":"2021-11-18 16:32:01","Longi":"0","Lati":"0","Verified":"1"},{"Id":"482941","EventId":"1654","SectionId":"4","SubSectionId":"5","OrgNo":"2048","OrgMemNo":"","Question":"5","Answer":"13","Score":"13","Remarks":"","MonitorNo":"1","Status":"S","Updated_At":"2021-11-18 16:32:01","Longi":"0","Lati":"0","Verified":"1"},{"Id":"483087","EventId":"1654","SectionId":"4","SubSectionId":"6","OrgNo":"2304","OrgMemNo":"000029","Question":"1","Answer":"0","Score":"1","Remarks":"ok","MonitorNo":"1","Status":"S","Updated_At":"2021-11-18 16:32:01","Longi":"0","Lati":"0","Verified":"1"},{"Id":"483096","EventId":"1654","SectionId":"4","SubSectionId":"6","OrgNo":"2271","OrgMemNo":"000134","Question":"1","Answer":"0","Score":"1","Remarks":"ok","MonitorNo":"1","Status":"S","Updated_At":"2021-11-18 16:32:01","Longi":"0","Lati":"0","Verified":"1"},{"Id":"483110","EventId":"1654","SectionId":"4","SubSectionId":"6","OrgNo":"5010","OrgMemNo":"000072","Question":"1","Answer":"0","Score":"1","Remarks":"ok","MonitorNo":"1","Status":"S","Updated_At":"2021-11-18 16:32:01","Longi":"0","Lati":"0","Verified":"1"},{"Id":"0","EventId":"1654","SectionId":"2","SubSectionId":"1","OrgNo":"5006","OrgMemNo":"000036","Question":"1","Answer":"0","Score":"1","Remarks":"","MonitorNo":"1","Status":"S","Updated_At":"2021-11-18 16:31:22","Longi":"0","Lati":"0","Verified":"1"},{"Id":"483531","EventId":"1654","SectionId":"2","SubSectionId":"3","OrgNo":"5006","OrgMemNo":"000036","Question":"1","Answer":"0","Score":"1","Remarks":"ok","MonitorNo":"1","Status":"S","Updated_At":"2021-11-18 16:31:22","Longi":"0","Lati":"0","Verified":"1"},{"Id":"483535","EventId":"1654","SectionId":"2","SubSectionId":"4","OrgNo":"5006","OrgMemNo":"000036","Question":"1","Answer":"0","Score":"1","Remarks":"","MonitorNo":"1","Status":"S","Updated_At":"2021-11-18 16:31:22","Longi":"0","Lati":"0","Verified":"1"},{"Id":"483536","EventId":"1654","SectionId":"2","SubSectionId":"4","OrgNo":"5006","OrgMemNo":"000036","Question":"2","Answer":"0","Score":"1","Remarks":"","MonitorNo":"1","Status":"S","Updated_At":"2021-11-18 16:31:22","Longi":"0","Lati":"0","Verified":"1"},{"Id":"483537","EventId":"1654","SectionId":"2","SubSectionId":"4","OrgNo":"5006","OrgMemNo":"000036","Question":"3","Answer":"0","Score":"1","Remarks":"","MonitorNo":"1","Status":"S","Updated_At":"2021-11-18 16:31:22","Longi":"0","Lati":"0","Verified":"1"},{"Id":"483538","EventId":"1654","SectionId":"2","SubSectionId":"5","OrgNo":"5006","OrgMemNo":"000036","Question":"1","Answer":"0","Score":"1","Remarks":"","MonitorNo":"1","Status":"S","Updated_At":"2021-11-18 16:31:22","Longi":"0","Lati":"0","Verified":"1"},{"Id":"483539","EventId":"1654","SectionId":"2","SubSectionId":"5","OrgNo":"5006","OrgMemNo":"000036","Question":"2","Answer":"1","Score":"0","Remarks":"","MonitorNo":"1","Status":"S","Updated_At":"2021-11-18 16:31:22","Longi":"0","Lati":"0","Verified":"1"},{"Id":"483540","EventId":"1654","SectionId":"2","SubSectionId":"5","OrgNo":"5006","OrgMemNo":"000036","Question":"3","Answer":"0","Score":"1","Remarks":"","MonitorNo":"1","Status":"S","Updated_At":"2021-11-18 16:31:22","Longi":"0","Lati":"0","Verified":"1"},{"Id":"483550","EventId":"1654","SectionId":"2","SubSectionId":"1","OrgNo":"5006","OrgMemNo":"000036","Question":"2","Answer":"1","Score":"0","Remarks":"","MonitorNo":"1","Status":"S","Updated_At":"2021-11-18 16:31:22","Longi":"0","Lati":"0","Verified":"1"},{"Id":"483551","EventId":"1654","SectionId":"2","SubSectionId":"1","OrgNo":"5006","OrgMemNo":"000036","Question":"3","Answer":"1","Score":"0","Remarks":"","MonitorNo":"1","Status":"S","Updated_At":"2021-11-18 16:31:22","Longi":"0","Lati":"0","Verified":"1"},{"Id":"483552","EventId":"1654","SectionId":"2","SubSectionId":"1","OrgNo":"5006","OrgMemNo":"000036","Question":"4","Answer":"1","Score":"0","Remarks":"","MonitorNo":"1","Status":"S","Updated_At":"2021-11-18 16:31:22","Longi":"0","Lati":"0","Verified":"1"},{"Id":"483553","EventId":"1654","SectionId":"2","SubSectionId":"2","OrgNo":"5006","OrgMemNo":"000036","Question":"1","Answer":"0","Score":"1","Remarks":"","MonitorNo":"1","Status":"S","Updated_At":"2021-11-18 16:31:22","Longi":"0","Lati":"0","Verified":"1"},{"Id":"483554","EventId":"1654","SectionId":"2","SubSectionId":"2","OrgNo":"5006","OrgMemNo":"000036","Question":"2","Answer":"1","Score":"0","Remarks":"","MonitorNo":"1","Status":"S","Updated_At":"2021-11-18 16:31:22","Longi":"0","Lati":"0","Verified":"1"},{"Id":"483555","EventId":"1654","SectionId":"2","SubSectionId":"2","OrgNo":"5006","OrgMemNo":"000036","Question":"3","Answer":"1","Score":"0","Remarks":"","MonitorNo":"1","Status":"S","Updated_At":"2021-11-18 16:31:22","Longi":"0","Lati":"0","Verified":"1"},{"Id":"483621","EventId":"1654","SectionId":"4","SubSectionId":"2","OrgNo":"5006","OrgMemNo":"","Question":"1","Answer":"1","Score":"0","Remarks":"","MonitorNo":"1","Status":"S","Updated_At":"2021-11-18 16:32:01","Longi":"0","Lati":"0","Verified":"1"},{"Id":"483622","EventId":"1654","SectionId":"4","SubSectionId":"2","OrgNo":"5006","OrgMemNo":"","Question":"2","Answer":"1","Score":"0","Remarks":"","MonitorNo":"1","Status":"S","Updated_At":"2021-11-18 16:32:01","Longi":"0","Lati":"0","Verified":"1"},{"Id":"483766","EventId":"1654","SectionId":"4","SubSectionId":"3","OrgNo":"5006","OrgMemNo":"","Question":"1","Answer":"1","Score":"0","Remarks":"","MonitorNo":"1","Status":"S","Updated_At":"2021-11-18 16:32:01","Longi":"0","Lati":"0","Verified":"1"},{"Id":"483767","EventId":"1654","SectionId":"4","SubSectionId":"3","OrgNo":"5006","OrgMemNo":"","Question":"2","Answer":"1","Score":"0","Remarks":"","MonitorNo":"1","Status":"S","Updated_At":"2021-11-18 16:32:01","Longi":"0","Lati":"0","Verified":"1"},{"Id":"483768","EventId":"1654","SectionId":"4","SubSectionId":"3","OrgNo":"5006","OrgMemNo":"","Question":"3","Answer":"1","Score":"0","Remarks":"","MonitorNo":"1","Status":"S","Updated_At":"2021-11-18 16:32:01","Longi":"0","Lati":"0","Verified":"1"},{"Id":"483769","EventId":"1654","SectionId":"4","SubSectionId":"3","OrgNo":"5006","OrgMemNo":"","Question":"4","Answer":"1","Score":"0","Remarks":"","MonitorNo":"1","Status":"S","Updated_At":"2021-11-18 16:32:01","Longi":"0","Lati":"0","Verified":"1"},{"Id":"483878","EventId":"1654","SectionId":"4","SubSectionId":"2","OrgNo":"5006","OrgMemNo":"","Question":"3","Answer":"0","Score":"1","Remarks":"","MonitorNo":"1","Status":"S","Updated_At":"2021-11-18 16:32:01","Longi":"0","Lati":"0","Verified":"1"},{"Id":"483879","EventId":"1654","SectionId":"4","SubSectionId":"2","OrgNo":"5006","OrgMemNo":"","Question":"4","Answer":"1","Score":"0","Remarks":"","MonitorNo":"1","Status":"S","Updated_At":"2021-11-18 16:32:01","Longi":"0","Lati":"0","Verified":"1"},{"Id":"483880","EventId":"1654","SectionId":"4","SubSectionId":"2","OrgNo":"5006","OrgMemNo":"","Question":"5","Answer":"1","Score":"0","Remarks":"","MonitorNo":"1","Status":"S","Updated_At":"2021-11-18 16:32:01","Longi":"0","Lati":"0","Verified":"1"},{"Id":"483881","EventId":"1654","SectionId":"4","SubSectionId":"2","OrgNo":"5006","OrgMemNo":"","Question":"6","Answer":"1","Score":"0","Remarks":"","MonitorNo":"1","Status":"S","Updated_At":"2021-11-18 16:32:01","Longi":"0","Lati":"0","Verified":"1"},{"Id":"0","EventId":"1654","SectionId":"3","SubSectionId":"0","OrgNo":"","OrgMemNo":"","Question":"1","Answer":"0","Score":"1","Remarks":"","MonitorNo":"1","Status":"N","Updated_At":"2021-11-18 16:31:29","Longi":"0","Lati":"0","Verified":"1"},{"Id":"483918","EventId":"1654","SectionId":"3","SubSectionId":"1","OrgNo":"","OrgMemNo":"","Question":"1","Answer":"12","Score":"12","Remarks":"","MonitorNo":"1","Status":"S","Updated_At":"2021-11-18 16:31:37","Longi":"0","Lati":"0","Verified":"1"},{"Id":"483975","EventId":"1654","SectionId":"3","SubSectionId":"1","OrgNo":"","OrgMemNo":"","Question":"2","Answer":"0","Score":"0","Remarks":"No clients received PD0","MonitorNo":"1","Status":"S","Updated_At":"2021-11-18 16:31:37","Longi":"0","Lati":"0","Verified":"1"},{"Id":"483976","EventId":"1654","SectionId":"3","SubSectionId":"2","OrgNo":"","OrgMemNo":"","Question":"1","Answer":"0","Score":"1","Remarks":"","MonitorNo":"1","Status":"S","Updated_At":"2021-11-18 16:31:36","Longi":"0","Lati":"0","Verified":"1"},{"Id":"483977","EventId":"1654","SectionId":"3","SubSectionId":"2","OrgNo":"","OrgMemNo":"","Question":"2","Answer":"0","Score":"1","Remarks":"","MonitorNo":"1","Status":"S","Updated_At":"2021-11-18 16:31:36","Longi":"0","Lati":"0","Verified":"1"},{"Id":"483978","EventId":"1654","SectionId":"3","SubSectionId":"2","OrgNo":"","OrgMemNo":"","Question":"3","Answer":"0","Score":"1","Remarks":"ok","MonitorNo":"1","Status":"S","Updated_At":"2021-11-18 16:31:36","Longi":"0","Lati":"0","Verified":"1"},{"Id":"484127","EventId":"1654","SectionId":"3","SubSectionId":"3","OrgNo":"2015","OrgMemNo":"000404","Question":"1","Answer":"0","Score":"1","Remarks":"","MonitorNo":"1","Status":"S","Updated_At":"2021-11-18 16:31:37","Longi":"0","Lati":"0","Verified":"1"},{"Id":"484128","EventId":"1654","SectionId":"3","SubSectionId":"3","OrgNo":"2015","OrgMemNo":"000404","Question":"2","Answer":"1","Score":"0","Remarks":"","MonitorNo":"1","Status":"S","Updated_At":"2021-11-18 16:31:37","Longi":"0","Lati":"0","Verified":"1"},{"Id":"484129","EventId":"1654","SectionId":"3","SubSectionId":"3","OrgNo":"2015","OrgMemNo":"000404","Question":"3","Answer":"1","Score":"0","Remarks":"","MonitorNo":"1","Status":"S","Updated_At":"2021-11-18 16:31:37","Longi":"0","Lati":"0","Verified":"1"},{"Id":"484130","EventId":"1654","SectionId":"3","SubSectionId":"4","OrgNo":"2015","OrgMemNo":"000404","Question":"1","Answer":"0","Score":"1","Remarks":"","MonitorNo":"1","Status":"S","Updated_At":"2021-11-18 16:31:37","Longi":"0","Lati":"0","Verified":"1"},{"Id":"484131","EventId":"1654","SectionId":"3","SubSectionId":"5","OrgNo":"2015","OrgMemNo":"000404","Question":"1","Answer":"0","Score":"1","Remarks":"","MonitorNo":"1","Status":"S","Updated_At":"2021-11-18 16:31:37","Longi":"0","Lati":"0","Verified":"1"},{"Id":"484137","EventId":"1654","SectionId":"3","SubSectionId":"3","OrgNo":"2337","OrgMemNo":"000183","Question":"1","Answer":"0","Score":"1","Remarks":"","MonitorNo":"1","Status":"S","Updated_At":"2021-11-18 16:31:37","Longi":"0","Lati":"0","Verified":"1"},{"Id":"484138","EventId":"1654","SectionId":"3","SubSectionId":"3","OrgNo":"2337","OrgMemNo":"000183","Question":"2","Answer":"1","Score":"0","Remarks":"","MonitorNo":"1","Status":"S","Updated_At":"2021-11-18 16:31:37","Longi":"0","Lati":"0","Verified":"1"},{"Id":"484139","EventId":"1654","SectionId":"3","SubSectionId":"3","OrgNo":"2337","OrgMemNo":"000183","Question":"3","Answer":"1","Score":"0","Remarks":"","MonitorNo":"1","Status":"S","Updated_At":"2021-11-18 16:31:37","Longi":"0","Lati":"0","Verified":"1"},{"Id":"484140","EventId":"1654","SectionId":"3","SubSectionId":"4","OrgNo":"2337","OrgMemNo":"000183","Question":"1","Answer":"1","Score":"0","Remarks":"","MonitorNo":"1","Status":"S","Updated_At":"2021-11-18 16:31:37","Longi":"0","Lati":"0","Verified":"1"},{"Id":"484141","EventId":"1654","SectionId":"3","SubSectionId":"5","OrgNo":"2337","OrgMemNo":"000183","Question":"1","Answer":"0","Score":"1","Remarks":"","MonitorNo":"1","Status":"S","Updated_At":"2021-11-18 16:31:37","Longi":"0","Lati":"0","Verified":"1"},{"Id":"484147","EventId":"1654","SectionId":"3","SubSectionId":"3","OrgNo":"2358","OrgMemNo":"000025","Question":"1","Answer":"0","Score":"1","Remarks":"","MonitorNo":"1","Status":"S","Updated_At":"2021-11-18 16:31:37","Longi":"0","Lati":"0","Verified":"1"},{"Id":"484148","EventId":"1654","SectionId":"3","SubSectionId":"3","OrgNo":"2358","OrgMemNo":"000025","Question":"2","Answer":"1","Score":"0","Remarks":"","MonitorNo":"1","Status":"S","Updated_At":"2021-11-18 16:31:37","Longi":"0","Lati":"0","Verified":"1"},{"Id":"484149","EventId":"1654","SectionId":"3","SubSectionId":"3","OrgNo":"2358","OrgMemNo":"000025","Question":"3","Answer":"0","Score":"1","Remarks":"","MonitorNo":"1","Status":"S","Updated_At":"2021-11-18 16:31:37","Longi":"0","Lati":"0","Verified":"1"},{"Id":"484150","EventId":"1654","SectionId":"3","SubSectionId":"4","OrgNo":"2358","OrgMemNo":"000025","Question":"1","Answer":"0","Score":"1","Remarks":"","MonitorNo":"1","Status":"S","Updated_At":"2021-11-18 16:31:37","Longi":"0","Lati":"0","Verified":"1"},{"Id":"484151","EventId":"1654","SectionId":"3","SubSectionId":"5","OrgNo":"2358","OrgMemNo":"000025","Question":"1","Answer":"0","Score":"1","Remarks":"","MonitorNo":"1","Status":"S","Updated_At":"2021-11-18 16:31:37","Longi":"0","Lati":"0","Verified":"1"},{"Id":"484152","EventId":"1654","SectionId":"3","SubSectionId":"3","OrgNo":"2268","OrgMemNo":"000275","Question":"1","Answer":"0","Score":"1","Remarks":"","MonitorNo":"1","Status":"S","Updated_At":"2021-11-18 16:31:37","Longi":"0","Lati":"0","Verified":"1"},{"Id":"484153","EventId":"1654","SectionId":"3","SubSectionId":"3","OrgNo":"2268","OrgMemNo":"000275","Question":"2","Answer":"1","Score":"0","Remarks":"","MonitorNo":"1","Status":"S","Updated_At":"2021-11-18 16:31:37","Longi":"0","Lati":"0","Verified":"1"},{"Id":"484154","EventId":"1654","SectionId":"3","SubSectionId":"3","OrgNo":"2268","OrgMemNo":"000275","Question":"3","Answer":"1","Score":"0","Remarks":"","MonitorNo":"1","Status":"S","Updated_At":"2021-11-18 16:31:37","Longi":"0","Lati":"0","Verified":"1"},{"Id":"484155","EventId":"1654","SectionId":"3","SubSectionId":"4","OrgNo":"2268","OrgMemNo":"000275","Question":"1","Answer":"0","Score":"1","Remarks":"","MonitorNo":"1","Status":"S","Updated_At":"2021-11-18 16:31:37","Longi":"0","Lati":"0","Verified":"1"},{"Id":"484156","EventId":"1654","SectionId":"3","SubSectionId":"5","OrgNo":"2268","OrgMemNo":"000275","Question":"1","Answer":"0","Score":"1","Remarks":"","MonitorNo":"1","Status":"S","Updated_At":"2021-11-18 16:31:37","Longi":"0","Lati":"0","Verified":"1"},{"Id":"484174","EventId":"1654","SectionId":"3","SubSectionId":"3","OrgNo":"2331","OrgMemNo":"000071","Question":"1","Answer":"0","Score":"1","Remarks":"","MonitorNo":"1","Status":"S","Updated_At":"2021-11-18 16:31:37","Longi":"0","Lati":"0","Verified":"1"},{"Id":"484175","EventId":"1654","SectionId":"3","SubSectionId":"3","OrgNo":"2331","OrgMemNo":"000071","Question":"2","Answer":"1","Score":"0","Remarks":"","MonitorNo":"1","Status":"S","Updated_At":"2021-11-18 16:31:37","Longi":"0","Lati":"0","Verified":"1"},{"Id":"484176","EventId":"1654","SectionId":"3","SubSectionId":"3","OrgNo":"2331","OrgMemNo":"000071","Question":"3","Answer":"0","Score":"1","Remarks":"","MonitorNo":"1","Status":"S","Updated_At":"2021-11-18 16:31:37","Longi":"0","Lati":"0","Verified":"1"},{"Id":"484177","EventId":"1654","SectionId":"3","SubSectionId":"4","OrgNo":"2331","OrgMemNo":"000071","Question":"1","Answer":"0","Score":"1","Remarks":"","MonitorNo":"1","Status":"S","Updated_At":"2021-11-18 16:31:37","Longi":"0","Lati":"0","Verified":"1"},{"Id":"484178","EventId":"1654","SectionId":"3","SubSectionId":"5","OrgNo":"2331","OrgMemNo":"000071","Question":"1","Answer":"0","Score":"1","Remarks":"","MonitorNo":"1","Status":"S","Updated_At":"2021-11-18 16:31:37","Longi":"0","Lati":"0","Verified":"1"},{"Id":"484493","EventId":"1654","SectionId":"4","SubSectionId":"11","OrgNo":"2282","OrgMemNo":"000096","Question":"1","Answer":"0","Score":"1","Remarks":"","MonitorNo":"1","Status":"S","Updated_At":"2021-11-18 16:32:01","Longi":"0","Lati":"0","Verified":"1"},{"Id":"484494","EventId":"1654","SectionId":"4","SubSectionId":"11","OrgNo":"2282","OrgMemNo":"000096","Question":"2","Answer":"1","Score":"0","Remarks":"\u0995\u09b0\u09cd\u09ae\u09c0 \u0995\u09a4\u09c3\u0995 \u09ab\u09bf\u09b2\u09cd\u09a1\u09c7 \u09aa\u09b0\u09bf\u09b6\u09cb\u09a7  ","MonitorNo":"1","Status":"S","Updated_At":"2021-11-18 16:32:01","Longi":"0","Lati":"0","Verified":"1"},{"Id":"484618","EventId":"1654","SectionId":"4","SubSectionId":"11","OrgNo":"2197","OrgMemNo":"000338","Question":"1","Answer":"0","Score":"1","Remarks":"","MonitorNo":"1","Status":"S","Updated_At":"2021-11-18 16:32:01","Longi":"0","Lati":"0","Verified":"1"},{"Id":"484619","EventId":"1654","SectionId":"4","SubSectionId":"11","OrgNo":"2197","OrgMemNo":"000338","Question":"2","Answer":"1","Score":"0","Remarks":"\u0995\u09b0\u09cd\u09ae\u09c0 \u0995\u09a4\u09cd\u0995 \u09ab\u09bf\u09b2\u09cd\u09a1\u09c7 \u09aa\u09b0\u09bf\u09b6\u09cb\u09a7 ","MonitorNo":"1","Status":"S","Updated_At":"2021-11-18 16:32:01","Longi":"0","Lati":"0","Verified":"1"},{"Id":"484620","EventId":"1654","SectionId":"4","SubSectionId":"6","OrgNo":"2191","OrgMemNo":"000541","Question":"1","Answer":"0","Score":"1","Remarks":"ok","MonitorNo":"1","Status":"S","Updated_At":"2021-11-18 16:32:01","Longi":"0","Lati":"0","Verified":"1"},{"Id":"484621","EventId":"1654","SectionId":"4","SubSectionId":"6","OrgNo":"5004","OrgMemNo":"000194","Question":"1","Answer":"0","Score":"1","Remarks":"ok","MonitorNo":"1","Status":"S","Updated_At":"2021-11-18 16:32:01","Longi":"0","Lati":"0","Verified":"1"},{"Id":"484622","EventId":"1654","SectionId":"4","SubSectionId":"11","OrgNo":"2337","OrgMemNo":"000183","Question":"1","Answer":"0","Score":"1","Remarks":"","MonitorNo":"1","Status":"S","Updated_At":"2021-11-18 16:32:01","Longi":"0","Lati":"0","Verified":"1"},{"Id":"484623","EventId":"1654","SectionId":"4","SubSectionId":"11","OrgNo":"2337","OrgMemNo":"000183","Question":"2","Answer":"1","Score":"0","Remarks":"\u0995\u09b0\u09cd\u09ae\u09c0 \u0995\u09b0\u09cd\u09a4\u09c3\u0995  \u09ab\u09bf\u09b2\u09cd\u09a1\u09c7 \u09aa\u09b0\u09bf\u09b6\u09cb\u09a7 ","MonitorNo":"1","Status":"S","Updated_At":"2021-11-18 16:32:01","Longi":"0","Lati":"0","Verified":"1"},{"Id":"484767","EventId":"1654","SectionId":"4","SubSectionId":"11","OrgNo":"2071","OrgMemNo":"000698","Question":"1","Answer":"0","Score":"1","Remarks":"","MonitorNo":"1","Status":"S","Updated_At":"2021-11-18 16:32:01","Longi":"0","Lati":"0","Verified":"1"},{"Id":"484768","EventId":"1654","SectionId":"4","SubSectionId":"11","OrgNo":"2071","OrgMemNo":"000698","Question":"2","Answer":"1","Score":"0","Remarks":"\u0995\u09b0\u09cd\u09ae\u09c0 \u0995\u09a4\u09c3\u0995 \u09ab\u09bf\u09b2\u09cd\u09a1\u09c7 \u09aa\u09b0\u09bf\u09b6\u09cb\u09a7 ","MonitorNo":"1","Status":"S","Updated_At":"2021-11-18 16:32:01","Longi":"0","Lati":"0","Verified":"1"},{"Id":"484777","EventId":"1654","SectionId":"4","SubSectionId":"11","OrgNo":"2303","OrgMemNo":"000089","Question":"1","Answer":"0","Score":"1","Remarks":"","MonitorNo":"1","Status":"S","Updated_At":"2021-11-18 16:32:01","Longi":"0","Lati":"0","Verified":"1"},{"Id":"484778","EventId":"1654","SectionId":"4","SubSectionId":"11","OrgNo":"2303","OrgMemNo":"000089","Question":"2","Answer":"1","Score":"0","Remarks":"\u0995\u09b0\u09cd\u09ae\u09c0 \u0995\u09b0\u09cd\u09a4\u09c3\u0995  \u09ab\u09bf\u09b2\u09cd\u09a1\u09c7 \u09aa\u09b0\u09bf\u09b6\u09cb\u09a7 ","MonitorNo":"1","Status":"S","Updated_At":"2021-11-18 16:32:01","Longi":"0","Lati":"0","Verified":"1"},{"Id":"485616","EventId":"1654","SectionId":"2","SubSectionId":"1","OrgNo":"2239","OrgMemNo":"000390","Question":"1","Answer":"0","Score":"1","Remarks":"","MonitorNo":"1","Status":"S","Updated_At":"2021-11-18 16:31:22","Longi":"0","Lati":"0","Verified":"1"},{"Id":"485617","EventId":"1654","SectionId":"2","SubSectionId":"1","OrgNo":"2239","OrgMemNo":"000390","Question":"2","Answer":"1","Score":"0","Remarks":"","MonitorNo":"1","Status":"S","Updated_At":"2021-11-18 16:31:22","Longi":"0","Lati":"0","Verified":"1"},{"Id":"485618","EventId":"1654","SectionId":"2","SubSectionId":"1","OrgNo":"2239","OrgMemNo":"000390","Question":"3","Answer":"1","Score":"0","Remarks":"","MonitorNo":"1","Status":"S","Updated_At":"2021-11-18 16:31:22","Longi":"0","Lati":"0","Verified":"1"},{"Id":"485619","EventId":"1654","SectionId":"2","SubSectionId":"1","OrgNo":"2239","OrgMemNo":"000390","Question":"4","Answer":"1","Score":"0","Remarks":"","MonitorNo":"1","Status":"S","Updated_At":"2021-11-18 16:31:22","Longi":"0","Lati":"0","Verified":"1"},{"Id":"485620","EventId":"1654","SectionId":"2","SubSectionId":"2","OrgNo":"2239","OrgMemNo":"000390","Question":"1","Answer":"0","Score":"1","Remarks":"","MonitorNo":"1","Status":"S","Updated_At":"2021-11-18 16:31:22","Longi":"0","Lati":"0","Verified":"1"},{"Id":"485621","EventId":"1654","SectionId":"2","SubSectionId":"2","OrgNo":"2239","OrgMemNo":"000390","Question":"2","Answer":"0","Score":"1","Remarks":"","MonitorNo":"1","Status":"S","Updated_At":"2021-11-18 16:31:22","Longi":"0","Lati":"0","Verified":"1"},{"Id":"485622","EventId":"1654","SectionId":"2","SubSectionId":"2","OrgNo":"2239","OrgMemNo":"000390","Question":"3","Answer":"1","Score":"0","Remarks":"","MonitorNo":"1","Status":"S","Updated_At":"2021-11-18 16:31:22","Longi":"0","Lati":"0","Verified":"1"},{"Id":"0","EventId":"1654","SectionId":"2","SubSectionId":"3","OrgNo":"2239","OrgMemNo":"000390","Question":"1","Answer":"0","Score":"1","Remarks":"ok","MonitorNo":"1","Status":"S","Updated_At":"2021-11-18 16:31:22","Longi":"0","Lati":"0","Verified":"1"},{"Id":"0","EventId":"1654","SectionId":"2","SubSectionId":"4","OrgNo":"2239","OrgMemNo":"000390","Question":"1","Answer":"0","Score":"1","Remarks":"","MonitorNo":"1","Status":"S","Updated_At":"2021-11-18 16:31:22","Longi":"0","Lati":"0","Verified":"1"},{"Id":"0","EventId":"1654","SectionId":"2","SubSectionId":"4","OrgNo":"2239","OrgMemNo":"000390","Question":"2","Answer":"0","Score":"1","Remarks":"","MonitorNo":"1","Status":"S","Updated_At":"2021-11-18 16:31:22","Longi":"0","Lati":"0","Verified":"1"},{"Id":"0","EventId":"1654","SectionId":"2","SubSectionId":"4","OrgNo":"2239","OrgMemNo":"000390","Question":"3","Answer":"1","Score":"0","Remarks":"","MonitorNo":"1","Status":"S","Updated_At":"2021-11-18 16:31:22","Longi":"0","Lati":"0","Verified":"1"},{"Id":"0","EventId":"1654","SectionId":"2","SubSectionId":"5","OrgNo":"2239","OrgMemNo":"000390","Question":"1","Answer":"1","Score":"0","Remarks":"","MonitorNo":"1","Status":"S","Updated_At":"2021-11-18 16:31:22","Longi":"0","Lati":"0","Verified":"1"},{"Id":"0","EventId":"1654","SectionId":"2","SubSectionId":"5","OrgNo":"2239","OrgMemNo":"000390","Question":"2","Answer":"1","Score":"0","Remarks":"","MonitorNo":"1","Status":"S","Updated_At":"2021-11-18 16:31:22","Longi":"0","Lati":"0","Verified":"1"},{"Id":"0","EventId":"1654","SectionId":"2","SubSectionId":"5","OrgNo":"2239","OrgMemNo":"000390","Question":"3","Answer":"0","Score":"1","Remarks":"","MonitorNo":"1","Status":"S","Updated_At":"2021-11-18 16:31:22","Longi":"0","Lati":"0","Verified":"1"},{"Id":"485653","EventId":"1654","SectionId":"2","SubSectionId":"1","OrgNo":"2239","OrgMemNo":"000069","Question":"1","Answer":"0","Score":"1","Remarks":"","MonitorNo":"1","Status":"S","Updated_At":"2021-11-18 16:31:22","Longi":"0","Lati":"0","Verified":"1"},{"Id":"485654","EventId":"1654","SectionId":"2","SubSectionId":"1","OrgNo":"2239","OrgMemNo":"000069","Question":"2","Answer":"0","Score":"1","Remarks":"","MonitorNo":"1","Status":"S","Updated_At":"2021-11-18 16:31:22","Longi":"0","Lati":"0","Verified":"1"},{"Id":"485655","EventId":"1654","SectionId":"2","SubSectionId":"1","OrgNo":"2239","OrgMemNo":"000069","Question":"3","Answer":"1","Score":"0","Remarks":"","MonitorNo":"1","Status":"S","Updated_At":"2021-11-18 16:31:22","Longi":"0","Lati":"0","Verified":"1"},{"Id":"485656","EventId":"1654","SectionId":"2","SubSectionId":"1","OrgNo":"2239","OrgMemNo":"000069","Question":"4","Answer":"1","Score":"0","Remarks":"","MonitorNo":"1","Status":"S","Updated_At":"2021-11-18 16:31:22","Longi":"0","Lati":"0","Verified":"1"},{"Id":"485657","EventId":"1654","SectionId":"2","SubSectionId":"2","OrgNo":"2239","OrgMemNo":"000069","Question":"1","Answer":"0","Score":"1","Remarks":"","MonitorNo":"1","Status":"S","Updated_At":"2021-11-18 16:31:22","Longi":"0","Lati":"0","Verified":"1"},{"Id":"485658","EventId":"1654","SectionId":"2","SubSectionId":"2","OrgNo":"2239","OrgMemNo":"000069","Question":"2","Answer":"0","Score":"1","Remarks":"","MonitorNo":"1","Status":"S","Updated_At":"2021-11-18 16:31:22","Longi":"0","Lati":"0","Verified":"1"},{"Id":"485659","EventId":"1654","SectionId":"2","SubSectionId":"2","OrgNo":"2239","OrgMemNo":"000069","Question":"3","Answer":"1","Score":"0","Remarks":"","MonitorNo":"1","Status":"S","Updated_At":"2021-11-18 16:31:22","Longi":"0","Lati":"0","Verified":"1"},{"Id":"485675","EventId":"1654","SectionId":"2","SubSectionId":"3","OrgNo":"2239","OrgMemNo":"000069","Question":"1","Answer":"0","Score":"1","Remarks":"ok","MonitorNo":"1","Status":"S","Updated_At":"2021-11-18 16:31:22","Longi":"0","Lati":"0","Verified":"1"},{"Id":"485676","EventId":"1654","SectionId":"2","SubSectionId":"4","OrgNo":"2239","OrgMemNo":"000069","Question":"1","Answer":"0","Score":"1","Remarks":"","MonitorNo":"1","Status":"S","Updated_At":"2021-11-18 16:31:22","Longi":"0","Lati":"0","Verified":"1"},{"Id":"485677","EventId":"1654","SectionId":"2","SubSectionId":"4","OrgNo":"2239","OrgMemNo":"000069","Question":"2","Answer":"1","Score":"0","Remarks":"","MonitorNo":"1","Status":"S","Updated_At":"2021-11-18 16:31:22","Longi":"0","Lati":"0","Verified":"1"},{"Id":"485678","EventId":"1654","SectionId":"2","SubSectionId":"4","OrgNo":"2239","OrgMemNo":"000069","Question":"3","Answer":"1","Score":"0","Remarks":"","MonitorNo":"1","Status":"S","Updated_At":"2021-11-18 16:31:22","Longi":"0","Lati":"0","Verified":"1"},{"Id":"485679","EventId":"1654","SectionId":"2","SubSectionId":"5","OrgNo":"2239","OrgMemNo":"000069","Question":"1","Answer":"0","Score":"1","Remarks":"","MonitorNo":"1","Status":"S","Updated_At":"2021-11-18 16:31:22","Longi":"0","Lati":"0","Verified":"1"},{"Id":"485680","EventId":"1654","SectionId":"2","SubSectionId":"5","OrgNo":"2239","OrgMemNo":"000069","Question":"2","Answer":"0","Score":"1","Remarks":"","MonitorNo":"1","Status":"S","Updated_At":"2021-11-18 16:31:22","Longi":"0","Lati":"0","Verified":"1"},{"Id":"485681","EventId":"1654","SectionId":"2","SubSectionId":"5","OrgNo":"2239","OrgMemNo":"000069","Question":"3","Answer":"0","Score":"1","Remarks":"","MonitorNo":"1","Status":"S","Updated_At":"2021-11-18 16:31:22","Longi":"0","Lati":"0","Verified":"1"},{"Id":"485711","EventId":"1654","SectionId":"4","SubSectionId":"9","OrgNo":"2239","OrgMemNo":"000390","Question":"1","Answer":"0","Score":"1","Remarks":"ok","MonitorNo":"1","Status":"S","Updated_At":"2021-11-18 16:32:01","Longi":"0","Lati":"0","Verified":"1"},{"Id":"485811","EventId":"1654","SectionId":"4","SubSectionId":"2","OrgNo":"2239","OrgMemNo":"","Question":"1","Answer":"1","Score":"0","Remarks":"","MonitorNo":"1","Status":"S","Updated_At":"2021-11-18 16:32:01","Longi":"0","Lati":"0","Verified":"1"},{"Id":"485812","EventId":"1654","SectionId":"4","SubSectionId":"2","OrgNo":"2239","OrgMemNo":"","Question":"2","Answer":"1","Score":"0","Remarks":"","MonitorNo":"1","Status":"S","Updated_At":"2021-11-18 16:32:01","Longi":"0","Lati":"0","Verified":"1"},{"Id":"485813","EventId":"1654","SectionId":"4","SubSectionId":"2","OrgNo":"2239","OrgMemNo":"","Question":"3","Answer":"0","Score":"1","Remarks":"","MonitorNo":"1","Status":"S","Updated_At":"2021-11-18 16:32:01","Longi":"0","Lati":"0","Verified":"1"},{"Id":"485814","EventId":"1654","SectionId":"4","SubSectionId":"2","OrgNo":"2239","OrgMemNo":"","Question":"4","Answer":"0","Score":"1","Remarks":"","MonitorNo":"1","Status":"S","Updated_At":"2021-11-18 16:32:01","Longi":"0","Lati":"0","Verified":"1"},{"Id":"485815","EventId":"1654","SectionId":"4","SubSectionId":"2","OrgNo":"2239","OrgMemNo":"","Question":"5","Answer":"1","Score":"0","Remarks":"","MonitorNo":"1","Status":"S","Updated_At":"2021-11-18 16:32:01","Longi":"0","Lati":"0","Verified":"1"},{"Id":"485816","EventId":"1654","SectionId":"4","SubSectionId":"2","OrgNo":"2239","OrgMemNo":"","Question":"6","Answer":"1","Score":"0","Remarks":"","MonitorNo":"1","Status":"S","Updated_At":"2021-11-18 16:32:01","Longi":"0","Lati":"0","Verified":"1"},{"Id":"485817","EventId":"1654","SectionId":"4","SubSectionId":"3","OrgNo":"2239","OrgMemNo":"","Question":"1","Answer":"0","Score":"1","Remarks":"","MonitorNo":"1","Status":"S","Updated_At":"2021-11-18 16:32:01","Longi":"0","Lati":"0","Verified":"1"},{"Id":"485818","EventId":"1654","SectionId":"4","SubSectionId":"3","OrgNo":"2239","OrgMemNo":"","Question":"2","Answer":"0","Score":"1","Remarks":"","MonitorNo":"1","Status":"S","Updated_At":"2021-11-18 16:32:01","Longi":"0","Lati":"0","Verified":"1"},{"Id":"485819","EventId":"1654","SectionId":"4","SubSectionId":"3","OrgNo":"2239","OrgMemNo":"","Question":"3","Answer":"1","Score":"0","Remarks":"","MonitorNo":"1","Status":"S","Updated_At":"2021-11-18 16:32:01","Longi":"0","Lati":"0","Verified":"1"},{"Id":"485820","EventId":"1654","SectionId":"4","SubSectionId":"3","OrgNo":"2239","OrgMemNo":"","Question":"4","Answer":"1","Score":"0","Remarks":"","MonitorNo":"1","Status":"S","Updated_At":"2021-11-18 16:32:01","Longi":"0","Lati":"0","Verified":"1"},{"Id":"485838","EventId":"1654","SectionId":"4","SubSectionId":"7","OrgNo":"2239","OrgMemNo":"000039","Question":"1","Answer":"0","Score":"1","Remarks":"ok","MonitorNo":"1","Status":"S","Updated_At":"2021-11-18 16:32:01","Longi":"0","Lati":"0","Verified":"1"},{"Id":"485839","EventId":"1654","SectionId":"4","SubSectionId":"7","OrgNo":"2239","OrgMemNo":"000405","Question":"1","Answer":"0","Score":"1","Remarks":"ok","MonitorNo":"1","Status":"S","Updated_At":"2021-11-18 16:32:01","Longi":"0","Lati":"0","Verified":"1"},{"Id":"485903","EventId":"1654","SectionId":"4","SubSectionId":"9","OrgNo":"2239","OrgMemNo":"002248","Question":"1","Answer":"0","Score":"1","Remarks":"ok","MonitorNo":"1","Status":"S","Updated_At":"2021-11-18 16:32:01","Longi":"0","Lati":"0","Verified":"1"},{"Id":"486496","EventId":"1654","SectionId":"2","SubSectionId":"3","OrgNo":"2014","OrgMemNo":"000410","Question":"1","Answer":"0","Score":"1","Remarks":"ok","MonitorNo":"1","Status":"S","Updated_At":"2021-11-18 16:31:22","Longi":"0","Lati":"0","Verified":"1"},{"Id":"486497","EventId":"1654","SectionId":"2","SubSectionId":"4","OrgNo":"2014","OrgMemNo":"000410","Question":"1","Answer":"0","Score":"1","Remarks":"","MonitorNo":"1","Status":"S","Updated_At":"2021-11-18 16:31:22","Longi":"0","Lati":"0","Verified":"1"},{"Id":"486498","EventId":"1654","SectionId":"2","SubSectionId":"4","OrgNo":"2014","OrgMemNo":"000410","Question":"2","Answer":"1","Score":"0","Remarks":"","MonitorNo":"1","Status":"S","Updated_At":"2021-11-18 16:31:22","Longi":"0","Lati":"0","Verified":"1"},{"Id":"486499","EventId":"1654","SectionId":"2","SubSectionId":"4","OrgNo":"2014","OrgMemNo":"000410","Question":"3","Answer":"1","Score":"0","Remarks":"","MonitorNo":"1","Status":"S","Updated_At":"2021-11-18 16:31:22","Longi":"0","Lati":"0","Verified":"1"},{"Id":"486500","EventId":"1654","SectionId":"2","SubSectionId":"5","OrgNo":"2014","OrgMemNo":"000410","Question":"1","Answer":"0","Score":"1","Remarks":"","MonitorNo":"1","Status":"S","Updated_At":"2021-11-18 16:31:22","Longi":"0","Lati":"0","Verified":"1"},{"Id":"486501","EventId":"1654","SectionId":"2","SubSectionId":"5","OrgNo":"2014","OrgMemNo":"000410","Question":"2","Answer":"1","Score":"0","Remarks":"","MonitorNo":"1","Status":"S","Updated_At":"2021-11-18 16:31:22","Longi":"0","Lati":"0","Verified":"1"},{"Id":"486502","EventId":"1654","SectionId":"2","SubSectionId":"5","OrgNo":"2014","OrgMemNo":"000410","Question":"3","Answer":"0","Score":"1","Remarks":"","MonitorNo":"1","Status":"S","Updated_At":"2021-11-18 16:31:22","Longi":"0","Lati":"0","Verified":"1"},{"Id":"486516","EventId":"1654","SectionId":"4","SubSectionId":"10","OrgNo":"2014","OrgMemNo":"000410","Question":"1","Answer":"1","Score":"0","Remarks":"\u0997\u09cd\u09b0\u09c7\u09b8 \u09aa\u09bf\u09a1\u09bc\u09bf\u09af\u09bc\u09a1\u09c7 \u0995\u09bf\u09b8\u09cd\u09a4\u09bf \u0986\u09a6\u09be\u09af\u09bc \u0995\u09b0\u09be \u09b9\u09af\u09bc\u09c7\u099b\u09c7 , \u09aa\u09be\u09b6\u09ac\u0987 \u098f\u09a8\u09cd\u099f\u09cd\u09b0\u09bf \u09a8\u09be\u0987 \u09a6\u09bf\u09af\u09bc\u09c7 \u0995\u09ae\u09cd\u09aa\u09bf\u0989\u099f\u09be\u09b0 \u09b8\u09c0\u099f\u09c7 \u0995\u09bf\u09b8\u09cd\u09a4\u09bf \u09ea\u09e6\u09e6\u09e6  \u099f\u09be\u0995\u09be \u09ac\u09c7\u09b6\u09c0 \u099c\u09ae\u09be \u0986\u099b\u09c7 \u0964","MonitorNo":"1","Status":"S","Updated_At":"2021-11-18 16:32:01","Longi":"0","Lati":"0","Verified":"1"},{"Id":"486526","EventId":"1654","SectionId":"4","SubSectionId":"10","OrgNo":"2234","OrgMemNo":"000084","Question":"1","Answer":"1","Score":"0","Remarks":"\u0997\u09cd\u09b0\u09c7\u09b8 \u09aa\u09bf\u09a1\u09bc\u09bf\u09af\u09bc\u09a1\u09c7 \u0995\u09bf\u09b8\u09cd\u09a4\u09bf \u0986\u09a6\u09be\u09af\u09bc \u0995\u09b0\u09be \u09b9\u09af\u09bc\u09c7\u099b\u09c7 \u0964","MonitorNo":"1","Status":"S","Updated_At":"2021-11-18 16:32:01","Longi":"0","Lati":"0","Verified":"1"},{"Id":"486528","EventId":"1654","SectionId":"2","SubSectionId":"3","OrgNo":"2234","OrgMemNo":"000084","Question":"1","Answer":"0","Score":"1","Remarks":"ok","MonitorNo":"1","Status":"S","Updated_At":"2021-11-18 16:31:22","Longi":"0","Lati":"0","Verified":"1"},{"Id":"486529","EventId":"1654","SectionId":"2","SubSectionId":"4","OrgNo":"2234","OrgMemNo":"000084","Question":"1","Answer":"0","Score":"1","Remarks":"","MonitorNo":"1","Status":"S","Updated_At":"2021-11-18 16:31:22","Longi":"0","Lati":"0","Verified":"1"},{"Id":"486530","EventId":"1654","SectionId":"2","SubSectionId":"4","OrgNo":"2234","OrgMemNo":"000084","Question":"2","Answer":"1","Score":"0","Remarks":"","MonitorNo":"1","Status":"S","Updated_At":"2021-11-18 16:31:22","Longi":"0","Lati":"0","Verified":"1"},{"Id":"486531","EventId":"1654","SectionId":"2","SubSectionId":"4","OrgNo":"2234","OrgMemNo":"000084","Question":"3","Answer":"0","Score":"1","Remarks":"","MonitorNo":"1","Status":"S","Updated_At":"2021-11-18 16:31:22","Longi":"0","Lati":"0","Verified":"1"},{"Id":"486532","EventId":"1654","SectionId":"2","SubSectionId":"5","OrgNo":"2234","OrgMemNo":"000084","Question":"1","Answer":"0","Score":"1","Remarks":"","MonitorNo":"1","Status":"S","Updated_At":"2021-11-18 16:31:22","Longi":"0","Lati":"0","Verified":"1"},{"Id":"486533","EventId":"1654","SectionId":"2","SubSectionId":"5","OrgNo":"2234","OrgMemNo":"000084","Question":"2","Answer":"1","Score":"0","Remarks":"","MonitorNo":"1","Status":"S","Updated_At":"2021-11-18 16:31:22","Longi":"0","Lati":"0","Verified":"1"},{"Id":"486534","EventId":"1654","SectionId":"2","SubSectionId":"5","OrgNo":"2234","OrgMemNo":"000084","Question":"3","Answer":"0","Score":"1","Remarks":"","MonitorNo":"1","Status":"S","Updated_At":"2021-11-18 16:31:22","Longi":"0","Lati":"0","Verified":"1"},{"Id":"486535","EventId":"1654","SectionId":"2","SubSectionId":"3","OrgNo":"2338","OrgMemNo":"000041","Question":"1","Answer":"0","Score":"1","Remarks":"ok","MonitorNo":"1","Status":"S","Updated_At":"2021-11-18 16:31:22","Longi":"0","Lati":"0","Verified":"1"},{"Id":"486536","EventId":"1654","SectionId":"2","SubSectionId":"4","OrgNo":"2338","OrgMemNo":"000041","Question":"1","Answer":"0","Score":"1","Remarks":"","MonitorNo":"1","Status":"S","Updated_At":"2021-11-18 16:31:22","Longi":"0","Lati":"0","Verified":"1"},{"Id":"486537","EventId":"1654","SectionId":"2","SubSectionId":"4","OrgNo":"2338","OrgMemNo":"000041","Question":"2","Answer":"1","Score":"0","Remarks":"","MonitorNo":"1","Status":"S","Updated_At":"2021-11-18 16:31:22","Longi":"0","Lati":"0","Verified":"1"},{"Id":"486538","EventId":"1654","SectionId":"2","SubSectionId":"4","OrgNo":"2338","OrgMemNo":"000041","Question":"3","Answer":"0","Score":"1","Remarks":"","MonitorNo":"1","Status":"S","Updated_At":"2021-11-18 16:31:22","Longi":"0","Lati":"0","Verified":"1"},{"Id":"486539","EventId":"1654","SectionId":"2","SubSectionId":"5","OrgNo":"2338","OrgMemNo":"000041","Question":"1","Answer":"1","Score":"0","Remarks":"","MonitorNo":"1","Status":"S","Updated_At":"2021-11-18 16:31:22","Longi":"0","Lati":"0","Verified":"1"},{"Id":"486540","EventId":"1654","SectionId":"2","SubSectionId":"5","OrgNo":"2338","OrgMemNo":"000041","Question":"2","Answer":"1","Score":"0","Remarks":"","MonitorNo":"1","Status":"S","Updated_At":"2021-11-18 16:31:22","Longi":"0","Lati":"0","Verified":"1"},{"Id":"486541","EventId":"1654","SectionId":"2","SubSectionId":"5","OrgNo":"2338","OrgMemNo":"000041","Question":"3","Answer":"0","Score":"1","Remarks":"","MonitorNo":"1","Status":"S","Updated_At":"2021-11-18 16:31:22","Longi":"0","Lati":"0","Verified":"1"},{"Id":"486569","EventId":"1654","SectionId":"4","SubSectionId":"10","OrgNo":"2318","OrgMemNo":"000085","Question":"1","Answer":"1","Score":"0","Remarks":"\u0997\u09cd\u09b0\u09c7\u09b8 \u09aa\u09bf\u09a1\u09bc\u09bf\u09af\u09bc\u09a1\u09c7  \u0995\u09bf\u09b8\u09cd\u09a4\u09bf \u0986\u09a6\u09be\u09af\u09bc \u0995\u09b0\u09be \u09b9\u09af\u09bc\u09c7\u099b\u09c7 \u0964","MonitorNo":"1","Status":"S","Updated_At":"2021-11-18 16:32:01","Longi":"0","Lati":"0","Verified":"1"},{"Id":"486570","EventId":"1654","SectionId":"2","SubSectionId":"3","OrgNo":"2318","OrgMemNo":"000085","Question":"1","Answer":"0","Score":"1","Remarks":"ok","MonitorNo":"1","Status":"S","Updated_At":"2021-11-18 16:31:22","Longi":"0","Lati":"0","Verified":"1"},{"Id":"486571","EventId":"1654","SectionId":"2","SubSectionId":"4","OrgNo":"2318","OrgMemNo":"000085","Question":"1","Answer":"1","Score":"0","Remarks":"","MonitorNo":"1","Status":"S","Updated_At":"2021-11-18 16:31:22","Longi":"0","Lati":"0","Verified":"1"},{"Id":"486572","EventId":"1654","SectionId":"2","SubSectionId":"4","OrgNo":"2318","OrgMemNo":"000085","Question":"2","Answer":"1","Score":"0","Remarks":"","MonitorNo":"1","Status":"S","Updated_At":"2021-11-18 16:31:22","Longi":"0","Lati":"0","Verified":"1"},{"Id":"486573","EventId":"1654","SectionId":"2","SubSectionId":"4","OrgNo":"2318","OrgMemNo":"000085","Question":"3","Answer":"1","Score":"0","Remarks":"","MonitorNo":"1","Status":"S","Updated_At":"2021-11-18 16:31:22","Longi":"0","Lati":"0","Verified":"1"},{"Id":"486574","EventId":"1654","SectionId":"2","SubSectionId":"5","OrgNo":"2318","OrgMemNo":"000085","Question":"1","Answer":"1","Score":"0","Remarks":"","MonitorNo":"1","Status":"S","Updated_At":"2021-11-18 16:31:22","Longi":"0","Lati":"0","Verified":"1"},{"Id":"486575","EventId":"1654","SectionId":"2","SubSectionId":"5","OrgNo":"2318","OrgMemNo":"000085","Question":"2","Answer":"1","Score":"0","Remarks":"","MonitorNo":"1","Status":"S","Updated_At":"2021-11-18 16:31:22","Longi":"0","Lati":"0","Verified":"1"},{"Id":"486576","EventId":"1654","SectionId":"2","SubSectionId":"5","OrgNo":"2318","OrgMemNo":"000085","Question":"3","Answer":"0","Score":"1","Remarks":"","MonitorNo":"1","Status":"S","Updated_At":"2021-11-18 16:31:22","Longi":"0","Lati":"0","Verified":"1"},{"Id":"486655","EventId":"1654","SectionId":"4","SubSectionId":"10","OrgNo":"2175","OrgMemNo":"003096","Question":"1","Answer":"1","Score":"0","Remarks":"\u0997\u09cd\u09b0\u09c7\u09b8 \u09aa\u09bf\u09a1\u09bc\u09bf\u09af\u09bc\u09a1\u09c7 \u0995\u09bf\u09b8\u09cd\u09a4\u09bf  \u0986\u09a6\u09be\u09af\u09bc \u0995\u09b0\u09be \u09b9\u09af\u09bc\u09c7\u099b\u09c7 \u0964","MonitorNo":"1","Status":"S","Updated_At":"2021-11-18 16:32:01","Longi":"0","Lati":"0","Verified":"1"},{"Id":"486657","EventId":"1654","SectionId":"2","SubSectionId":"3","OrgNo":"2175","OrgMemNo":"003096","Question":"1","Answer":"0","Score":"1","Remarks":"ok","MonitorNo":"1","Status":"S","Updated_At":"2021-11-18 16:31:22","Longi":"0","Lati":"0","Verified":"1"},{"Id":"486658","EventId":"1654","SectionId":"2","SubSectionId":"4","OrgNo":"2175","OrgMemNo":"003096","Question":"1","Answer":"0","Score":"1","Remarks":"","MonitorNo":"1","Status":"S","Updated_At":"2021-11-18 16:31:22","Longi":"0","Lati":"0","Verified":"1"},{"Id":"486659","EventId":"1654","SectionId":"2","SubSectionId":"4","OrgNo":"2175","OrgMemNo":"003096","Question":"2","Answer":"1","Score":"0","Remarks":"","MonitorNo":"1","Status":"S","Updated_At":"2021-11-18 16:31:22","Longi":"0","Lati":"0","Verified":"1"},{"Id":"486660","EventId":"1654","SectionId":"2","SubSectionId":"4","OrgNo":"2175","OrgMemNo":"003096","Question":"3","Answer":"1","Score":"0","Remarks":"","MonitorNo":"1","Status":"S","Updated_At":"2021-11-18 16:31:22","Longi":"0","Lati":"0","Verified":"1"},{"Id":"486661","EventId":"1654","SectionId":"2","SubSectionId":"5","OrgNo":"2175","OrgMemNo":"003096","Question":"1","Answer":"1","Score":"0","Remarks":"","MonitorNo":"1","Status":"S","Updated_At":"2021-11-18 16:31:22","Longi":"0","Lati":"0","Verified":"1"},{"Id":"486662","EventId":"1654","SectionId":"2","SubSectionId":"5","OrgNo":"2175","OrgMemNo":"003096","Question":"2","Answer":"1","Score":"0","Remarks":"","MonitorNo":"1","Status":"S","Updated_At":"2021-11-18 16:31:22","Longi":"0","Lati":"0","Verified":"1"},{"Id":"486663","EventId":"1654","SectionId":"2","SubSectionId":"5","OrgNo":"2175","OrgMemNo":"003096","Question":"3","Answer":"0","Score":"1","Remarks":"","MonitorNo":"1","Status":"S","Updated_At":"2021-11-18 16:31:22","Longi":"0","Lati":"0","Verified":"1"},{"Id":"486852","EventId":"1654","SectionId":"4","SubSectionId":"10","OrgNo":"2338","OrgMemNo":"000041","Question":"1","Answer":"1","Score":"0","Remarks":"\u0997\u09cd\u09b0\u09c7\u09b8 \u09aa\u09bf\u09a1\u09bc\u09bf\u09af\u09bc\u09a1\u09c7 \u0995\u09bf\u09b8\u09cd\u09a4\u09bf \u0986\u09a6\u09be\u09af\u09bc \u0995\u09b0\u09be \u09b9\u09af\u09bc\u09c7\u099b\u09c7 \u0964","MonitorNo":"1","Status":"S","Updated_At":"2021-11-18 16:32:01","Longi":"0","Lati":"0","Verified":"1"},{"Id":"487467","EventId":"1654","SectionId":"5","SubSectionId":"3","OrgNo":"2271","OrgMemNo":"000126","Question":"1","Answer":"0","Score":"1","Remarks":"ok","MonitorNo":"1","Status":"S","Updated_At":"2021-11-18 16:32:32","Longi":"0","Lati":"0","Verified":"1"},{"Id":"487468","EventId":"1654","SectionId":"5","SubSectionId":"3","OrgNo":"2304","OrgMemNo":"000119","Question":"1","Answer":"0","Score":"1","Remarks":"ok","MonitorNo":"1","Status":"S","Updated_At":"2021-11-18 16:32:32","Longi":"0","Lati":"0","Verified":"1"},{"Id":"487533","EventId":"1654","SectionId":"5","SubSectionId":"3","OrgNo":"2015","OrgMemNo":"000392","Question":"1","Answer":"0","Score":"1","Remarks":"ok","MonitorNo":"1","Status":"S","Updated_At":"2021-11-18 16:32:32","Longi":"0","Lati":"0","Verified":"1"},{"Id":"487534","EventId":"1654","SectionId":"5","SubSectionId":"3","OrgNo":"2195","OrgMemNo":"000557","Question":"1","Answer":"0","Score":"1","Remarks":"ok","MonitorNo":"1","Status":"S","Updated_At":"2021-11-18 16:32:32","Longi":"0","Lati":"0","Verified":"1"},{"Id":"487623","EventId":"1654","SectionId":"5","SubSectionId":"3","OrgNo":"2282","OrgMemNo":"000341","Question":"1","Answer":"0","Score":"1","Remarks":"ok","MonitorNo":"1","Status":"S","Updated_At":"2021-11-18 16:32:32","Longi":"0","Lati":"0","Verified":"1"},{"Id":"487624","EventId":"1654","SectionId":"5","SubSectionId":"3","OrgNo":"2318","OrgMemNo":"000004","Question":"1","Answer":"0","Score":"1","Remarks":"ok","MonitorNo":"1","Status":"S","Updated_At":"2021-11-18 16:32:32","Longi":"0","Lati":"0","Verified":"1"},{"Id":"487680","EventId":"1654","SectionId":"5","SubSectionId":"1","OrgNo":"","OrgMemNo":"","Question":"1","Answer":"1","Score":"0","Remarks":"","MonitorNo":"1","Status":"S","Updated_At":"2021-11-18 16:32:32","Longi":"0","Lati":"0","Verified":"1"},{"Id":"487681","EventId":"1654","SectionId":"5","SubSectionId":"2","OrgNo":"","OrgMemNo":"","Question":"1","Answer":"0","Score":"0","Remarks":"","MonitorNo":"1","Status":"S","Updated_At":"2021-11-18 16:32:32","Longi":"0","Lati":"0","Verified":"1"},{"Id":"487682","EventId":"1654","SectionId":"5","SubSectionId":"2","OrgNo":"","OrgMemNo":"","Question":"2","Answer":"0","Score":"0","Remarks":"Bm.\u098f\u09b0 \u09ae\u09be\u09b8\u09bf\u0995 \u0995\u09b0\u09cd\u09ae \u09aa\u09b0\u09bf\u0995\u09b2\u09cd\u09aa\u09a8\u09be \u09aa\u09be\u0993\u09df\u09be \u09af\u09be\u09af\u09bc\u09a8\u09bf \u0964","MonitorNo":"1","Status":"S","Updated_At":"2021-11-18 16:32:32","Longi":"0","Lati":"0","Verified":"1"},{"Id":"487683","EventId":"1654","SectionId":"5","SubSectionId":"6","OrgNo":"","OrgMemNo":"","Question":"1","Answer":"0","Score":"6","Remarks":"ok","MonitorNo":"1","Status":"S","Updated_At":"2021-11-18 16:32:32","Longi":"0","Lati":"0","Verified":"1"},{"Id":"487684","EventId":"1654","SectionId":"5","SubSectionId":"6","OrgNo":"","OrgMemNo":"","Question":"2","Answer":"0","Score":"1","Remarks":"","MonitorNo":"1","Status":"S","Updated_At":"2021-11-18 16:32:32","Longi":"0","Lati":"0","Verified":"1"},{"Id":"487685","EventId":"1654","SectionId":"5","SubSectionId":"7","OrgNo":"","OrgMemNo":"","Question":"1","Answer":"0","Score":"6","Remarks":"ok","MonitorNo":"1","Status":"S","Updated_At":"2021-11-18 16:32:32","Longi":"0","Lati":"0","Verified":"1"},{"Id":"487686","EventId":"1654","SectionId":"5","SubSectionId":"8","OrgNo":"","OrgMemNo":"","Question":"1","Answer":"0","Score":"6","Remarks":"","MonitorNo":"1","Status":"S","Updated_At":"2021-11-18 16:32:32","Longi":"0","Lati":"0","Verified":"1"},{"Id":"487687","EventId":"1654","SectionId":"5","SubSectionId":"9","OrgNo":"","OrgMemNo":"","Question":"1","Answer":"0","Score":"6","Remarks":"","MonitorNo":"1","Status":"S","Updated_At":"2021-11-18 16:32:32","Longi":"0","Lati":"0","Verified":"1"},{"Id":"487688","EventId":"1654","SectionId":"5","SubSectionId":"10","OrgNo":"","OrgMemNo":"","Question":"1","Answer":"0","Score":"6","Remarks":"","MonitorNo":"1","Status":"S","Updated_At":"2021-11-18 16:32:32","Longi":"0","Lati":"0","Verified":"1"},{"Id":"487694","EventId":"1654","SectionId":"5","SubSectionId":"11","OrgNo":"","OrgMemNo":"","Question":"1","Answer":"0","Score":"6","Remarks":"ok","MonitorNo":"1","Status":"S","Updated_At":"2021-11-18 16:32:32","Longi":"0","Lati":"0","Verified":"1"},{"Id":"487695","EventId":"1654","SectionId":"5","SubSectionId":"12","OrgNo":"","OrgMemNo":"","Question":"1","Answer":"0","Score":"6","Remarks":"ok","MonitorNo":"1","Status":"S","Updated_At":"2021-11-18 16:32:32","Longi":"0","Lati":"0","Verified":"1"},{"Id":"487696","EventId":"1654","SectionId":"5","SubSectionId":"13","OrgNo":"","OrgMemNo":"","Question":"1","Answer":"1","Score":"0","Remarks":"\u09ae\u09cd\u09af\u09be\u09a8\u09c7\u099c\u09be\u09b0 \u09a8\u09bf\u09af\u09bc\u09ae\u09bf\u09a4 \u0986\u09a6\u09be\u09af\u09bc  \u09b0\u09c7\u099c\u09bf\u09b8\u09cd\u099f\u09cd\u09b0\u09be\u09b0 \u09b8\u09cd\u09ac\u09be\u0995\u09cd\u09b7\u09b0 \u0995\u09b0\u09c7\u09a8 \u09a8\u09be \u0964","MonitorNo":"1","Status":"S","Updated_At":"2021-11-18 16:32:32","Longi":"0","Lati":"0","Verified":"1"}]}]}